<?xml version="1.0" encoding="utf-8"?>
<integrationbase>
  <product>
    <sku>96833182</sku>
    <name>MEMBRANSATS</name>
    <status>enabled</status>
    <attributes store="admin">
      <status>1</status>
      <c4_status>8</c4_status>
      <m3_status>20</m3_status>
      <is_returnable>0</is_returnable>
      <allow_purchase>1</allow_purchase>
      <allow_guest_purchase>1</allow_guest_purchase>
      <allow_backorders>1</allow_backorders>
      <manufacturer></manufacturer>
      <c4_sysid>1201076</c4_sysid>
      <ean_number>7320460361187</ean_number>
      <updated_at>2021-01-07T19:01:16.908000</updated_at>
      <dangerous_goods>0</dangerous_goods>
      <competitor_references>&quot;&quot;</competitor_references>
      <supplier>002</supplier>
      <visibility>both</visibility>
    </attributes>
    <attributes store="01">
      <allow_purchase>0</allow_purchase>
      <allow_guest_purchase>0</allow_guest_purchase>
      <price>3202.000000</price>
      <visibility>none</visibility>
    </attributes>
    <attributes store="02">
      <allow_purchase>0</allow_purchase>
      <visibility>none</visibility>
    </attributes>
    <attributes store="66">
      <allow_purchase>0</allow_purchase>
      <visibility>none</visibility>
    </attributes>
    <links>
      <link type="relation"/>
    </links>
    <type>simple</type>
  </product>
  <product>
    <sku>85208641</sku>
    <name>LÄTTVIKTSSTÖVEL 41</name>
    <status>enabled</status>
    <attributes store="admin">
      <status>1</status>
      <c4_status>8</c4_status>
      <m3_status>20</m3_status>
      <is_returnable>0</is_returnable>
      <allow_purchase>1</allow_purchase>
      <allow_guest_purchase>1</allow_guest_purchase>
      <allow_backorders>1</allow_backorders>
      <manufacturer></manufacturer>
      <c4_sysid>1161183</c4_sysid>
      <ean_number>7320466005412</ean_number>
      <updated_at>2021-01-07T19:01:17.049000</updated_at>
      <dangerous_goods>0</dangerous_goods>
      <competitor_references>&quot;&quot;</competitor_references>
      <supplier>002</supplier>
      <visibility>both</visibility>
    </attributes>
    <attributes store="01">
      <allow_purchase>0</allow_purchase>
      <allow_guest_purchase>0</allow_guest_purchase>
      <price>889.000000</price>
      <visibility>none</visibility>
    </attributes>
    <attributes store="02">
      <allow_purchase>0</allow_purchase>
      <visibility>none</visibility>
    </attributes>
    <attributes store="66">
      <allow_purchase>0</allow_purchase>
      <visibility>none</visibility>
    </attributes>
    <links>
      <link type="relation"/>
    </links>
    <type>simple</type>
  </product>
  <product>
    <sku>EL848078</sku>
    <name>Hydraulicpump (Dubbel), Komple</name>
    <status>enabled</status>
    <attributes store="admin">
      <status>1</status>
      <c4_status>5</c4_status>
      <m3_status>20</m3_status>
      <is_returnable>0</is_returnable>
      <allow_purchase>1</allow_purchase>
      <allow_guest_purchase>1</allow_guest_purchase>
      <allow_backorders>1</allow_backorders>
      <manufacturer></manufacturer>
      <c4_sysid>1231958</c4_sysid>
      <qty_increments>0.000000</qty_increments>
      <updated_at>2021-01-07T19:01:17.205000</updated_at>
      <dangerous_goods>0</dangerous_goods>
      <competitor_references>&quot;&quot;</competitor_references>
      <supplier>887</supplier>
      <visibility>both</visibility>
    </attributes>
    <attributes store="01">
      <allow_purchase>1</allow_purchase>
      <allow_guest_purchase>1</allow_guest_purchase>
      <visibility>both</visibility>
    </attributes>
    <attributes store="02">
      <allow_purchase>1</allow_purchase>
      <price>31861.000000</price>
      <visibility>both</visibility>
    </attributes>
    <attributes store="66">
      <allow_purchase>1</allow_purchase>
      <visibility>both</visibility>
    </attributes>
    <links>
      <link type="relation"/>
    </links>
    <type>simple</type>
  </product>
  <product>
    <sku>EL472033</sku>
    <name>ROTORPINNE</name>
    <status>enabled</status>
    <attributes store="admin">
      <status>1</status>
      <c4_status>5</c4_status>
      <m3_status>20</m3_status>
      <is_returnable>0</is_returnable>
      <allow_purchase>1</allow_purchase>
      <allow_guest_purchase>1</allow_guest_purchase>
      <allow_backorders>1</allow_backorders>
      <manufacturer></manufacturer>
      <c4_sysid>1220915</c4_sysid>
      <qty_increments>0.000000</qty_increments>
      <updated_at>2021-01-07T19:01:17.346000</updated_at>
      <dangerous_goods>0</dangerous_goods>
      <competitor_references>&quot;&quot;</competitor_references>
      <supplier>887</supplier>
      <visibility>both</visibility>
    </attributes>
    <attributes store="01">
      <allow_purchase>1</allow_purchase>
      <allow_guest_purchase>1</allow_guest_purchase>
      <visibility>both</visibility>
    </attributes>
    <attributes store="02">
      <allow_purchase>1</allow_purchase>
      <price>215.000000</price>
      <visibility>both</visibility>
    </attributes>
    <attributes store="66">
      <allow_purchase>1</allow_purchase>
      <visibility>both</visibility>
    </attributes>
    <links>
      <link type="relation"/>
    </links>
    <type>simple</type>
  </product>
  <product>
    <sku>EL805412</sku>
    <name>Axle</name>
    <status>enabled</status>
    <attributes store="admin">
      <status>1</status>
      <c4_status>5</c4_status>
      <m3_status>20</m3_status>
      <is_returnable>0</is_returnable>
      <allow_purchase>1</allow_purchase>
      <allow_guest_purchase>1</allow_guest_purchase>
      <allow_backorders>1</allow_backorders>
      <manufacturer></manufacturer>
      <c4_sysid>1233521</c4_sysid>
      <qty_increments>0.000000</qty_increments>
      <updated_at>2021-01-07T19:01:17.502000</updated_at>
      <dangerous_goods>0</dangerous_goods>
      <competitor_references>&quot;&quot;</competitor_references>
      <supplier>887</supplier>
      <visibility>both</visibility>
    </attributes>
    <attributes store="01">
      <allow_purchase>1</allow_purchase>
      <allow_guest_purchase>1</allow_guest_purchase>
      <visibility>both</visibility>
    </attributes>
    <attributes store="02">
      <allow_purchase>1</allow_purchase>
      <price>780.000000</price>
      <visibility>both</visibility>
    </attributes>
    <attributes store="66">
      <allow_purchase>1</allow_purchase>
      <visibility>both</visibility>
    </attributes>
    <links>
      <link type="relation"/>
    </links>
    <type>simple</type>
  </product>
  <product>
    <sku>EL140399</sku>
    <name>Bearing 22212 E C3</name>
    <status>enabled</status>
    <attributes store="admin">
      <status>1</status>
      <c4_status>5</c4_status>
      <m3_status>20</m3_status>
      <is_returnable>0</is_returnable>
      <allow_purchase>1</allow_purchase>
      <allow_guest_purchase>1</allow_guest_purchase>
      <allow_backorders>1</allow_backorders>
      <manufacturer></manufacturer>
      <c4_sysid>1226754</c4_sysid>
      <qty_increments>0.000000</qty_increments>
      <updated_at>2021-01-07T19:01:17.674000</updated_at>
      <dangerous_goods>0</dangerous_goods>
      <competitor_references>&quot;&quot;</competitor_references>
      <supplier>887</supplier>
      <visibility>both</visibility>
    </attributes>
    <attributes store="01">
      <allow_purchase>1</allow_purchase>
      <allow_guest_purchase>1</allow_guest_purchase>
      <visibility>both</visibility>
    </attributes>
    <attributes store="02">
      <allow_purchase>1</allow_purchase>
      <price>2847.000000</price>
      <visibility>both</visibility>
    </attributes>
    <attributes store="66">
      <allow_purchase>1</allow_purchase>
      <visibility>both</visibility>
    </attributes>
    <links>
      <link type="relation"/>
    </links>
    <type>simple</type>
  </product>
  <product>
    <sku>EL579456</sku>
    <name>Tarpaulin rear</name>
    <status>enabled</status>
    <attributes store="admin">
      <status>1</status>
      <c4_status>5</c4_status>
      <m3_status>20</m3_status>
      <is_returnable>0</is_returnable>
      <allow_purchase>1</allow_purchase>
      <allow_guest_purchase>1</allow_guest_purchase>
      <allow_backorders>1</allow_backorders>
      <manufacturer></manufacturer>
      <c4_sysid>1314083</c4_sysid>
      <qty_increments>0.000000</qty_increments>
      <updated_at>2021-01-07T19:01:17.830000</updated_at>
      <dangerous_goods>0</dangerous_goods>
      <competitor_references>&quot;&quot;</competitor_references>
      <supplier>887</supplier>
      <visibility>both</visibility>
    </attributes>
    <attributes store="01">
      <allow_purchase>1</allow_purchase>
      <allow_guest_purchase>1</allow_guest_purchase>
      <visibility>both</visibility>
    </attributes>
    <attributes store="02">
      <allow_purchase>1</allow_purchase>
      <price>2220.000000</price>
      <visibility>both</visibility>
    </attributes>
    <attributes store="66">
      <allow_purchase>1</allow_purchase>
      <visibility>both</visibility>
    </attributes>
    <links>
      <link type="relation"/>
    </links>
    <type>simple</type>
  </product>
  <product>
    <sku>EL455280</sku>
    <name>Bracket</name>
    <status>enabled</status>
    <attributes store="admin">
      <status>1</status>
      <c4_status>5</c4_status>
      <m3_status>20</m3_status>
      <is_returnable>0</is_returnable>
      <allow_purchase>1</allow_purchase>
      <allow_guest_purchase>1</allow_guest_purchase>
      <allow_backorders>1</allow_backorders>
      <manufacturer></manufacturer>
      <c4_sysid>1220704</c4_sysid>
      <qty_increments>0.000000</qty_increments>
      <updated_at>2021-01-07T19:01:17.986000</updated_at>
      <dangerous_goods>0</dangerous_goods>
      <competitor_references>&quot;&quot;</competitor_references>
      <supplier>887</supplier>
      <visibility>both</visibility>
    </attributes>
    <attributes store="01">
      <allow_purchase>1</allow_purchase>
      <allow_guest_purchase>1</allow_guest_purchase>
      <visibility>both</visibility>
    </attributes>
    <attributes store="02">
      <allow_purchase>1</allow_purchase>
      <price>4713.000000</price>
      <visibility>both</visibility>
    </attributes>
    <attributes store="66">
      <allow_purchase>1</allow_purchase>
      <visibility>both</visibility>
    </attributes>
    <links>
      <link type="relation"/>
    </links>
    <type>simple</type>
  </product>
  <product>
    <sku>EL416030</sku>
    <name>Basket compl. VT 750 right</name>
    <status>enabled</status>
    <attributes store="admin">
      <status>1</status>
      <c4_status>5</c4_status>
      <m3_status>20</m3_status>
      <is_returnable>0</is_returnable>
      <allow_purchase>1</allow_purchase>
      <allow_guest_purchase>1</allow_guest_purchase>
      <allow_backorders>1</allow_backorders>
      <manufacturer></manufacturer>
      <c4_sysid>1216445</c4_sysid>
      <qty_increments>0.000000</qty_increments>
      <updated_at>2021-01-07T19:01:18.142000</updated_at>
      <dangerous_goods>0</dangerous_goods>
      <competitor_references>&quot;&quot;</competitor_references>
      <supplier>887</supplier>
      <visibility>both</visibility>
    </attributes>
    <attributes store="01">
      <allow_purchase>1</allow_purchase>
      <allow_guest_purchase>1</allow_guest_purchase>
      <visibility>both</visibility>
    </attributes>
    <attributes store="02">
      <allow_purchase>1</allow_purchase>
      <price>122963.000000</price>
      <visibility>both</visibility>
    </attributes>
    <attributes store="66">
      <allow_purchase>1</allow_purchase>
      <visibility>both</visibility>
    </attributes>
    <links>
      <link type="relation"/>
    </links>
    <type>simple</type>
  </product>
  <product>
    <sku>EL828132</sku>
    <name>Bearing house</name>
    <status>enabled</status>
    <attributes store="admin">
      <status>1</status>
      <c4_status>5</c4_status>
      <m3_status>20</m3_status>
      <is_returnable>0</is_returnable>
      <allow_purchase>1</allow_purchase>
      <allow_guest_purchase>1</allow_guest_purchase>
      <allow_backorders>1</allow_backorders>
      <manufacturer></manufacturer>
      <c4_sysid>1215221</c4_sysid>
      <qty_increments>0.000000</qty_increments>
      <updated_at>2021-01-07T19:01:18.283000</updated_at>
      <dangerous_goods>0</dangerous_goods>
      <competitor_references>&quot;&quot;</competitor_references>
      <supplier>887</supplier>
      <visibility>both</visibility>
    </attributes>
    <attributes store="01">
      <allow_purchase>1</allow_purchase>
      <allow_guest_purchase>1</allow_guest_purchase>
      <visibility>both</visibility>
    </attributes>
    <attributes store="02">
      <allow_purchase>1</allow_purchase>
      <price>9638.000000</price>
      <visibility>both</visibility>
    </attributes>
    <attributes store="66">
      <allow_purchase>1</allow_purchase>
      <visibility>both</visibility>
    </attributes>
    <links>
      <link type="relation"/>
    </links>
    <type>simple</type>
  </product>
  <product>
    <sku>EL546335</sku>
    <name>Front hood</name>
    <status>enabled</status>
    <attributes store="admin">
      <status>1</status>
      <c4_status>5</c4_status>
      <m3_status>20</m3_status>
      <is_returnable>0</is_returnable>
      <allow_purchase>1</allow_purchase>
      <allow_guest_purchase>1</allow_guest_purchase>
      <allow_backorders>1</allow_backorders>
      <manufacturer></manufacturer>
      <c4_sysid>1219399</c4_sysid>
      <qty_increments>0.000000</qty_increments>
      <updated_at>2021-01-07T19:01:18.439000</updated_at>
      <dangerous_goods>0</dangerous_goods>
      <competitor_references>&quot;&quot;</competitor_references>
      <supplier>887</supplier>
      <visibility>both</visibility>
    </attributes>
    <attributes store="01">
      <allow_purchase>1</allow_purchase>
      <allow_guest_purchase>1</allow_guest_purchase>
      <visibility>both</visibility>
    </attributes>
    <attributes store="02">
      <allow_purchase>1</allow_purchase>
      <price>4409.000000</price>
      <visibility>both</visibility>
    </attributes>
    <attributes store="66">
      <allow_purchase>1</allow_purchase>
      <visibility>both</visibility>
    </attributes>
    <links>
      <link type="relation"/>
    </links>
    <type>simple</type>
  </product>
  <product>
    <sku>3020070</sku>
    <name>NUT M24 ZN DIN 935</name>
    <status>enabled</status>
    <attributes store="admin">
      <status>1</status>
      <c4_status>5</c4_status>
      <m3_status>20</m3_status>
      <is_returnable>0</is_returnable>
      <allow_purchase>1</allow_purchase>
      <allow_guest_purchase>1</allow_guest_purchase>
      <allow_backorders>1</allow_backorders>
      <manufacturer></manufacturer>
      <c4_sysid>1710027</c4_sysid>
      <qty_increments>1.000000</qty_increments>
      <ean_number>7322235887786</ean_number>
      <updated_at>2021-01-07T19:01:18.580000</updated_at>
      <dangerous_goods>0</dangerous_goods>
      <competitor_references>&quot;&quot;</competitor_references>
      <supplier>174</supplier>
      <visibility>both</visibility>
    </attributes>
    <attributes store="01">
      <allow_purchase>1</allow_purchase>
      <allow_guest_purchase>1</allow_guest_purchase>
      <price>59.000000</price>
      <visibility>both</visibility>
    </attributes>
    <attributes store="02">
      <allow_purchase>1</allow_purchase>
      <visibility>both</visibility>
    </attributes>
    <attributes store="66">
      <allow_purchase>1</allow_purchase>
      <price>60.000000</price>
      <visibility>both</visibility>
    </attributes>
    <links>
      <link type="relation"/>
    </links>
    <type>simple</type>
  </product>
  <product>
    <sku>EL545489</sku>
    <name>Tarpaulin right</name>
    <status>enabled</status>
    <attributes store="admin">
      <status>1</status>
      <c4_status>5</c4_status>
      <m3_status>20</m3_status>
      <is_returnable>0</is_returnable>
      <allow_purchase>1</allow_purchase>
      <allow_guest_purchase>1</allow_guest_purchase>
      <allow_backorders>1</allow_backorders>
      <manufacturer></manufacturer>
      <c4_sysid>1235147</c4_sysid>
      <qty_increments>0.000000</qty_increments>
      <updated_at>2021-01-07T19:01:18.752000</updated_at>
      <dangerous_goods>0</dangerous_goods>
      <competitor_references>&quot;&quot;</competitor_references>
      <supplier>887</supplier>
      <visibility>both</visibility>
    </attributes>
    <attributes store="01">
      <allow_purchase>1</allow_purchase>
      <allow_guest_purchase>1</allow_guest_purchase>
      <visibility>both</visibility>
    </attributes>
    <attributes store="02">
      <allow_purchase>1</allow_purchase>
      <price>2888.000000</price>
      <visibility>both</visibility>
    </attributes>
    <attributes store="66">
      <allow_purchase>1</allow_purchase>
      <visibility>both</visibility>
    </attributes>
    <links>
      <link type="relation"/>
    </links>
    <type>simple</type>
  </product>
  <product>
    <sku>89863538</sku>
    <name>MOTOR 230V INKL KRETSK</name>
    <status>enabled</status>
    <attributes store="admin">
      <status>1</status>
      <c4_status>8</c4_status>
      <m3_status>20</m3_status>
      <is_returnable>0</is_returnable>
      <allow_purchase>1</allow_purchase>
      <allow_guest_purchase>1</allow_guest_purchase>
      <allow_backorders>1</allow_backorders>
      <manufacturer></manufacturer>
      <c4_sysid>1146279</c4_sysid>
      <ean_number>7320461087468</ean_number>
      <updated_at>2021-01-07T19:01:18.908000</updated_at>
      <dangerous_goods>0</dangerous_goods>
      <competitor_references>&quot;&quot;</competitor_references>
      <supplier>002</supplier>
      <visibility>both</visibility>
    </attributes>
    <attributes store="01">
      <allow_purchase>0</allow_purchase>
      <allow_guest_purchase>0</allow_guest_purchase>
      <price>8040.000000</price>
      <visibility>none</visibility>
    </attributes>
    <attributes store="02">
      <allow_purchase>0</allow_purchase>
      <visibility>none</visibility>
    </attributes>
    <attributes store="66">
      <allow_purchase>0</allow_purchase>
      <visibility>none</visibility>
    </attributes>
    <links>
      <link type="relation"/>
    </links>
    <type>simple</type>
  </product>
  <product>
    <sku>EL143390</sku>
    <name>Hydr.Accumulator</name>
    <status>enabled</status>
    <attributes store="admin">
      <status>1</status>
      <c4_status>5</c4_status>
      <m3_status>20</m3_status>
      <is_returnable>0</is_returnable>
      <allow_purchase>1</allow_purchase>
      <allow_guest_purchase>1</allow_guest_purchase>
      <allow_backorders>1</allow_backorders>
      <manufacturer></manufacturer>
      <c4_sysid>1225981</c4_sysid>
      <qty_increments>0.000000</qty_increments>
      <updated_at>2021-01-07T19:01:19.064000</updated_at>
      <dangerous_goods>0</dangerous_goods>
      <competitor_references>&quot;&quot;</competitor_references>
      <supplier>887</supplier>
      <visibility>both</visibility>
    </attributes>
    <attributes store="01">
      <allow_purchase>1</allow_purchase>
      <allow_guest_purchase>1</allow_guest_purchase>
      <visibility>both</visibility>
    </attributes>
    <attributes store="02">
      <allow_purchase>1</allow_purchase>
      <price>6780.000000</price>
      <visibility>both</visibility>
    </attributes>
    <attributes store="66">
      <allow_purchase>1</allow_purchase>
      <visibility>both</visibility>
    </attributes>
    <links>
      <link type="relation"/>
    </links>
    <type>simple</type>
  </product>
  <product>
    <sku>EL508515</sku>
    <name>Låsring 80(0.404.7.111.00)</name>
    <status>enabled</status>
    <attributes store="admin">
      <status>1</status>
      <c4_status>5</c4_status>
      <m3_status>20</m3_status>
      <is_returnable>0</is_returnable>
      <allow_purchase>1</allow_purchase>
      <allow_guest_purchase>1</allow_guest_purchase>
      <allow_backorders>1</allow_backorders>
      <manufacturer></manufacturer>
      <c4_sysid>1226989</c4_sysid>
      <qty_increments>0.000000</qty_increments>
      <updated_at>2021-01-07T19:01:19.221000</updated_at>
      <dangerous_goods>0</dangerous_goods>
      <competitor_references>&quot;&quot;</competitor_references>
      <supplier>887</supplier>
      <visibility>both</visibility>
    </attributes>
    <attributes store="01">
      <allow_purchase>1</allow_purchase>
      <allow_guest_purchase>1</allow_guest_purchase>
      <visibility>both</visibility>
    </attributes>
    <attributes store="02">
      <allow_purchase>1</allow_purchase>
      <price>83.000000</price>
      <visibility>both</visibility>
    </attributes>
    <attributes store="66">
      <allow_purchase>1</allow_purchase>
      <visibility>both</visibility>
    </attributes>
    <links>
      <link type="relation"/>
    </links>
    <type>simple</type>
  </product>
  <product>
    <sku>EL450061</sku>
    <name>Steel slicer</name>
    <status>enabled</status>
    <attributes store="admin">
      <status>1</status>
      <c4_status>5</c4_status>
      <m3_status>20</m3_status>
      <is_returnable>0</is_returnable>
      <allow_purchase>1</allow_purchase>
      <allow_guest_purchase>1</allow_guest_purchase>
      <allow_backorders>1</allow_backorders>
      <manufacturer></manufacturer>
      <c4_sysid>1225026</c4_sysid>
      <qty_increments>0.000000</qty_increments>
      <updated_at>2021-01-07T19:01:19.361000</updated_at>
      <dangerous_goods>0</dangerous_goods>
      <competitor_references>&quot;&quot;</competitor_references>
      <supplier>887</supplier>
      <visibility>both</visibility>
    </attributes>
    <attributes store="01">
      <allow_purchase>1</allow_purchase>
      <allow_guest_purchase>1</allow_guest_purchase>
      <visibility>both</visibility>
    </attributes>
    <attributes store="02">
      <allow_purchase>1</allow_purchase>
      <price>23541.000000</price>
      <visibility>both</visibility>
    </attributes>
    <attributes store="66">
      <allow_purchase>1</allow_purchase>
      <visibility>both</visibility>
    </attributes>
    <links>
      <link type="relation"/>
    </links>
    <type>simple</type>
  </product>
  <product>
    <sku>98932781</sku>
    <name>VATTENKOPP C20 3/4&quot; ANSL ANV T</name>
    <status>enabled</status>
    <attributes store="admin">
      <status>1</status>
      <c4_status>8</c4_status>
      <m3_status>20</m3_status>
      <is_returnable>0</is_returnable>
      <allow_purchase>1</allow_purchase>
      <allow_guest_purchase>1</allow_guest_purchase>
      <allow_backorders>1</allow_backorders>
      <manufacturer></manufacturer>
      <c4_sysid>1175986</c4_sysid>
      <ean_number>7320460506014</ean_number>
      <updated_at>2021-01-07T19:01:19.517000</updated_at>
      <dangerous_goods>0</dangerous_goods>
      <competitor_references>&quot;&quot;</competitor_references>
      <supplier>002</supplier>
      <visibility>both</visibility>
    </attributes>
    <attributes store="01">
      <allow_purchase>0</allow_purchase>
      <allow_guest_purchase>0</allow_guest_purchase>
      <price>939.000000</price>
      <visibility>none</visibility>
    </attributes>
    <attributes store="02">
      <allow_purchase>0</allow_purchase>
      <visibility>none</visibility>
    </attributes>
    <attributes store="66">
      <allow_purchase>0</allow_purchase>
      <visibility>none</visibility>
    </attributes>
    <links>
      <link type="relation"/>
    </links>
    <type>simple</type>
  </product>
  <product>
    <sku>EL140970</sku>
    <name>Grease nipple M6x1</name>
    <status>enabled</status>
    <attributes store="admin">
      <status>1</status>
      <c4_status>5</c4_status>
      <m3_status>20</m3_status>
      <is_returnable>0</is_returnable>
      <allow_purchase>1</allow_purchase>
      <allow_guest_purchase>1</allow_guest_purchase>
      <allow_backorders>1</allow_backorders>
      <manufacturer></manufacturer>
      <c4_sysid>1235770</c4_sysid>
      <qty_increments>0.000000</qty_increments>
      <updated_at>2021-01-07T19:01:19.674000</updated_at>
      <dangerous_goods>0</dangerous_goods>
      <competitor_references>&quot;&quot;</competitor_references>
      <supplier>887</supplier>
      <visibility>both</visibility>
    </attributes>
    <attributes store="01">
      <allow_purchase>1</allow_purchase>
      <allow_guest_purchase>1</allow_guest_purchase>
      <visibility>both</visibility>
    </attributes>
    <attributes store="02">
      <allow_purchase>1</allow_purchase>
      <price>51.000000</price>
      <visibility>both</visibility>
    </attributes>
    <attributes store="66">
      <allow_purchase>1</allow_purchase>
      <visibility>both</visibility>
    </attributes>
    <links>
      <link type="relation"/>
    </links>
    <type>simple</type>
  </product>
  <product>
    <sku>EL152492</sku>
    <name>Clutch disc 8 pack</name>
    <status>enabled</status>
    <attributes store="admin">
      <status>1</status>
      <c4_status>5</c4_status>
      <m3_status>20</m3_status>
      <is_returnable>0</is_returnable>
      <allow_purchase>1</allow_purchase>
      <allow_guest_purchase>1</allow_guest_purchase>
      <allow_backorders>1</allow_backorders>
      <manufacturer></manufacturer>
      <c4_sysid>1232404</c4_sysid>
      <qty_increments>0.000000</qty_increments>
      <updated_at>2021-01-07T19:01:19.861000</updated_at>
      <dangerous_goods>0</dangerous_goods>
      <competitor_references>&quot;&quot;</competitor_references>
      <supplier>887</supplier>
      <visibility>both</visibility>
    </attributes>
    <attributes store="01">
      <allow_purchase>1</allow_purchase>
      <allow_guest_purchase>1</allow_guest_purchase>
      <visibility>both</visibility>
    </attributes>
    <attributes store="02">
      <allow_purchase>1</allow_purchase>
      <price>2545.000000</price>
      <visibility>both</visibility>
    </attributes>
    <attributes store="66">
      <allow_purchase>1</allow_purchase>
      <visibility>both</visibility>
    </attributes>
    <links>
      <link type="relation"/>
    </links>
    <type>simple</type>
  </product>
  <product>
    <sku>EL132824</sku>
    <name>Spring pin DIN 1481 6X50</name>
    <status>enabled</status>
    <attributes store="admin">
      <status>1</status>
      <c4_status>5</c4_status>
      <m3_status>20</m3_status>
      <is_returnable>0</is_returnable>
      <allow_purchase>1</allow_purchase>
      <allow_guest_purchase>1</allow_guest_purchase>
      <allow_backorders>1</allow_backorders>
      <manufacturer></manufacturer>
      <c4_sysid>1223327</c4_sysid>
      <qty_increments>0.000000</qty_increments>
      <updated_at>2021-01-07T19:01:20.002000</updated_at>
      <dangerous_goods>0</dangerous_goods>
      <competitor_references>&quot;&quot;</competitor_references>
      <supplier>887</supplier>
      <visibility>both</visibility>
    </attributes>
    <attributes store="01">
      <allow_purchase>1</allow_purchase>
      <allow_guest_purchase>1</allow_guest_purchase>
      <visibility>both</visibility>
    </attributes>
    <attributes store="02">
      <allow_purchase>1</allow_purchase>
      <price>48.000000</price>
      <visibility>both</visibility>
    </attributes>
    <attributes store="66">
      <allow_purchase>1</allow_purchase>
      <visibility>both</visibility>
    </attributes>
    <links>
      <link type="relation"/>
    </links>
    <type>simple</type>
  </product>
  <product>
    <sku>EL452630</sku>
    <name>Pin</name>
    <status>enabled</status>
    <attributes store="admin">
      <status>1</status>
      <c4_status>5</c4_status>
      <m3_status>20</m3_status>
      <is_returnable>0</is_returnable>
      <allow_purchase>1</allow_purchase>
      <allow_guest_purchase>1</allow_guest_purchase>
      <allow_backorders>1</allow_backorders>
      <manufacturer></manufacturer>
      <c4_sysid>1228533</c4_sysid>
      <qty_increments>0.000000</qty_increments>
      <updated_at>2021-01-07T19:01:20.174000</updated_at>
      <dangerous_goods>0</dangerous_goods>
      <competitor_references>&quot;&quot;</competitor_references>
      <supplier>887</supplier>
      <visibility>both</visibility>
    </attributes>
    <attributes store="01">
      <allow_purchase>1</allow_purchase>
      <allow_guest_purchase>1</allow_guest_purchase>
      <visibility>both</visibility>
    </attributes>
    <attributes store="02">
      <allow_purchase>1</allow_purchase>
      <price>351.000000</price>
      <visibility>both</visibility>
    </attributes>
    <attributes store="66">
      <allow_purchase>1</allow_purchase>
      <visibility>both</visibility>
    </attributes>
    <links>
      <link type="relation"/>
    </links>
    <type>simple</type>
  </product>
  <product>
    <sku>EL148883</sku>
    <name>Ram suction cup base</name>
    <status>enabled</status>
    <attributes store="admin">
      <status>1</status>
      <c4_status>5</c4_status>
      <m3_status>20</m3_status>
      <is_returnable>0</is_returnable>
      <allow_purchase>1</allow_purchase>
      <allow_guest_purchase>1</allow_guest_purchase>
      <allow_backorders>1</allow_backorders>
      <manufacturer></manufacturer>
      <c4_sysid>1232972</c4_sysid>
      <qty_increments>0.000000</qty_increments>
      <updated_at>2021-01-07T19:01:20.330000</updated_at>
      <dangerous_goods>0</dangerous_goods>
      <competitor_references>&quot;&quot;</competitor_references>
      <supplier>887</supplier>
      <visibility>both</visibility>
    </attributes>
    <attributes store="01">
      <allow_purchase>1</allow_purchase>
      <allow_guest_purchase>1</allow_guest_purchase>
      <visibility>both</visibility>
    </attributes>
    <attributes store="02">
      <allow_purchase>1</allow_purchase>
      <price>218.000000</price>
      <visibility>both</visibility>
    </attributes>
    <attributes store="66">
      <allow_purchase>1</allow_purchase>
      <visibility>both</visibility>
    </attributes>
    <links>
      <link type="relation"/>
    </links>
    <type>simple</type>
  </product>
  <product>
    <sku>EL801026</sku>
    <name>Hydraulic motor Geolink</name>
    <status>enabled</status>
    <attributes store="admin">
      <status>1</status>
      <c4_status>5</c4_status>
      <m3_status>20</m3_status>
      <is_returnable>0</is_returnable>
      <allow_purchase>1</allow_purchase>
      <allow_guest_purchase>1</allow_guest_purchase>
      <allow_backorders>1</allow_backorders>
      <manufacturer></manufacturer>
      <c4_sysid>1314117</c4_sysid>
      <qty_increments>0.000000</qty_increments>
      <updated_at>2021-01-07T19:01:20.486000</updated_at>
      <dangerous_goods>0</dangerous_goods>
      <competitor_references>&quot;&quot;</competitor_references>
      <supplier>887</supplier>
      <visibility>both</visibility>
    </attributes>
    <attributes store="01">
      <allow_purchase>1</allow_purchase>
      <allow_guest_purchase>1</allow_guest_purchase>
      <visibility>both</visibility>
    </attributes>
    <attributes store="02">
      <allow_purchase>1</allow_purchase>
      <price>13951.000000</price>
      <visibility>both</visibility>
    </attributes>
    <attributes store="66">
      <allow_purchase>1</allow_purchase>
      <visibility>both</visibility>
    </attributes>
    <links>
      <link type="relation"/>
    </links>
    <type>simple</type>
  </product>
  <product>
    <sku>5304760501</sku>
    <name>LAGERHYLSA</name>
    <status>enabled</status>
    <attributes store="admin">
      <status>1</status>
      <c4_status>8</c4_status>
      <m3_status>20</m3_status>
      <is_returnable>0</is_returnable>
      <allow_purchase>1</allow_purchase>
      <allow_guest_purchase>1</allow_guest_purchase>
      <allow_backorders>1</allow_backorders>
      <manufacturer></manufacturer>
      <c4_sysid>1143097</c4_sysid>
      <ean_number>7320460187671</ean_number>
      <updated_at>2021-01-07T19:01:20.658000</updated_at>
      <dangerous_goods>0</dangerous_goods>
      <competitor_references>&quot;&quot;</competitor_references>
      <supplier>002</supplier>
      <visibility>both</visibility>
    </attributes>
    <attributes store="01">
      <allow_purchase>0</allow_purchase>
      <allow_guest_purchase>0</allow_guest_purchase>
      <price>1114.000000</price>
      <visibility>none</visibility>
    </attributes>
    <attributes store="02">
      <allow_purchase>0</allow_purchase>
      <visibility>none</visibility>
    </attributes>
    <attributes store="66">
      <allow_purchase>0</allow_purchase>
      <visibility>none</visibility>
    </attributes>
    <links>
      <link type="relation"/>
    </links>
    <type>simple</type>
  </product>
  <product>
    <sku>EL140520</sku>
    <name>Bearing PF 25 FM SKF</name>
    <status>enabled</status>
    <attributes store="admin">
      <status>1</status>
      <c4_status>5</c4_status>
      <m3_status>20</m3_status>
      <is_returnable>0</is_returnable>
      <allow_purchase>1</allow_purchase>
      <allow_guest_purchase>1</allow_guest_purchase>
      <allow_backorders>1</allow_backorders>
      <manufacturer></manufacturer>
      <c4_sysid>1236199</c4_sysid>
      <qty_increments>0.000000</qty_increments>
      <updated_at>2021-01-07T19:01:20.814000</updated_at>
      <dangerous_goods>0</dangerous_goods>
      <competitor_references>&quot;&quot;</competitor_references>
      <supplier>887</supplier>
      <visibility>both</visibility>
    </attributes>
    <attributes store="01">
      <allow_purchase>1</allow_purchase>
      <allow_guest_purchase>1</allow_guest_purchase>
      <visibility>both</visibility>
    </attributes>
    <attributes store="02">
      <allow_purchase>1</allow_purchase>
      <price>987.000000</price>
      <visibility>both</visibility>
    </attributes>
    <attributes store="66">
      <allow_purchase>1</allow_purchase>
      <visibility>both</visibility>
    </attributes>
    <links>
      <link type="relation"/>
    </links>
    <type>simple</type>
  </product>
  <product>
    <sku>EL462310</sku>
    <name>Wheel axle</name>
    <status>enabled</status>
    <attributes store="admin">
      <status>1</status>
      <c4_status>5</c4_status>
      <m3_status>20</m3_status>
      <is_returnable>0</is_returnable>
      <allow_purchase>1</allow_purchase>
      <allow_guest_purchase>1</allow_guest_purchase>
      <allow_backorders>1</allow_backorders>
      <manufacturer></manufacturer>
      <c4_sysid>1313612</c4_sysid>
      <qty_increments>0.000000</qty_increments>
      <updated_at>2021-01-07T19:01:20.986000</updated_at>
      <dangerous_goods>0</dangerous_goods>
      <competitor_references>&quot;&quot;</competitor_references>
      <supplier>887</supplier>
      <visibility>both</visibility>
    </attributes>
    <attributes store="01">
      <allow_purchase>1</allow_purchase>
      <allow_guest_purchase>1</allow_guest_purchase>
      <visibility>both</visibility>
    </attributes>
    <attributes store="02">
      <allow_purchase>1</allow_purchase>
      <price>5473.000000</price>
      <visibility>both</visibility>
    </attributes>
    <attributes store="66">
      <allow_purchase>1</allow_purchase>
      <visibility>both</visibility>
    </attributes>
    <links>
      <link type="relation"/>
    </links>
    <type>simple</type>
  </product>
  <product>
    <sku>EL416220</sku>
    <name>Center linkarm</name>
    <status>enabled</status>
    <attributes store="admin">
      <status>1</status>
      <c4_status>5</c4_status>
      <m3_status>20</m3_status>
      <is_returnable>0</is_returnable>
      <allow_purchase>1</allow_purchase>
      <allow_guest_purchase>1</allow_guest_purchase>
      <allow_backorders>1</allow_backorders>
      <manufacturer></manufacturer>
      <c4_sysid>1215149</c4_sysid>
      <qty_increments>0.000000</qty_increments>
      <updated_at>2021-01-07T19:01:21.143000</updated_at>
      <dangerous_goods>0</dangerous_goods>
      <competitor_references>&quot;&quot;</competitor_references>
      <supplier>887</supplier>
      <visibility>both</visibility>
    </attributes>
    <attributes store="01">
      <allow_purchase>1</allow_purchase>
      <allow_guest_purchase>1</allow_guest_purchase>
      <visibility>both</visibility>
    </attributes>
    <attributes store="02">
      <allow_purchase>1</allow_purchase>
      <price>2803.000000</price>
      <visibility>both</visibility>
    </attributes>
    <attributes store="66">
      <allow_purchase>1</allow_purchase>
      <visibility>both</visibility>
    </attributes>
    <links>
      <link type="relation"/>
    </links>
    <type>simple</type>
  </product>
  <product>
    <sku>EL144498</sku>
    <name>Dual overcentre valve</name>
    <status>enabled</status>
    <attributes store="admin">
      <status>1</status>
      <c4_status>5</c4_status>
      <m3_status>20</m3_status>
      <is_returnable>0</is_returnable>
      <allow_purchase>1</allow_purchase>
      <allow_guest_purchase>1</allow_guest_purchase>
      <allow_backorders>1</allow_backorders>
      <manufacturer></manufacturer>
      <c4_sysid>1229973</c4_sysid>
      <qty_increments>0.000000</qty_increments>
      <updated_at>2021-01-07T19:01:21.314000</updated_at>
      <dangerous_goods>0</dangerous_goods>
      <competitor_references>&quot;&quot;</competitor_references>
      <supplier>887</supplier>
      <visibility>both</visibility>
    </attributes>
    <attributes store="01">
      <allow_purchase>1</allow_purchase>
      <allow_guest_purchase>1</allow_guest_purchase>
      <visibility>both</visibility>
    </attributes>
    <attributes store="02">
      <allow_purchase>1</allow_purchase>
      <price>4860.000000</price>
      <visibility>both</visibility>
    </attributes>
    <attributes store="66">
      <allow_purchase>1</allow_purchase>
      <visibility>both</visibility>
    </attributes>
    <links>
      <link type="relation"/>
    </links>
    <type>simple</type>
  </product>
  <product>
    <sku>EL133095</sku>
    <name>Cup bolts DIN 603 M 6X20 A2</name>
    <status>enabled</status>
    <attributes store="admin">
      <status>1</status>
      <c4_status>5</c4_status>
      <m3_status>20</m3_status>
      <is_returnable>0</is_returnable>
      <allow_purchase>1</allow_purchase>
      <allow_guest_purchase>1</allow_guest_purchase>
      <allow_backorders>1</allow_backorders>
      <manufacturer></manufacturer>
      <c4_sysid>1227628</c4_sysid>
      <qty_increments>0.000000</qty_increments>
      <updated_at>2021-01-07T19:01:21.471000</updated_at>
      <dangerous_goods>0</dangerous_goods>
      <competitor_references>&quot;&quot;</competitor_references>
      <supplier>887</supplier>
      <visibility>both</visibility>
    </attributes>
    <attributes store="01">
      <allow_purchase>1</allow_purchase>
      <allow_guest_purchase>1</allow_guest_purchase>
      <visibility>both</visibility>
    </attributes>
    <attributes store="02">
      <allow_purchase>1</allow_purchase>
      <price>31.000000</price>
      <visibility>both</visibility>
    </attributes>
    <attributes store="66">
      <allow_purchase>1</allow_purchase>
      <visibility>both</visibility>
    </attributes>
    <links>
      <link type="relation"/>
    </links>
    <type>simple</type>
  </product>
  <product>
    <sku>EL517529</sku>
    <name>Spacer</name>
    <status>enabled</status>
    <attributes store="admin">
      <status>1</status>
      <c4_status>5</c4_status>
      <m3_status>20</m3_status>
      <is_returnable>0</is_returnable>
      <allow_purchase>1</allow_purchase>
      <allow_guest_purchase>1</allow_guest_purchase>
      <allow_backorders>1</allow_backorders>
      <manufacturer></manufacturer>
      <c4_sysid>1217670</c4_sysid>
      <qty_increments>0.000000</qty_increments>
      <updated_at>2021-01-07T19:01:21.627000</updated_at>
      <dangerous_goods>0</dangerous_goods>
      <competitor_references>&quot;&quot;</competitor_references>
      <supplier>887</supplier>
      <visibility>both</visibility>
    </attributes>
    <attributes store="01">
      <allow_purchase>1</allow_purchase>
      <allow_guest_purchase>1</allow_guest_purchase>
      <visibility>both</visibility>
    </attributes>
    <attributes store="02">
      <allow_purchase>1</allow_purchase>
      <price>210.000000</price>
      <visibility>both</visibility>
    </attributes>
    <attributes store="66">
      <allow_purchase>1</allow_purchase>
      <visibility>both</visibility>
    </attributes>
    <links>
      <link type="relation"/>
    </links>
    <type>simple</type>
  </product>
  <product>
    <sku>EL158230</sku>
    <name>Gearbox housing</name>
    <status>enabled</status>
    <attributes store="admin">
      <status>1</status>
      <c4_status>5</c4_status>
      <m3_status>20</m3_status>
      <is_returnable>0</is_returnable>
      <allow_purchase>1</allow_purchase>
      <allow_guest_purchase>1</allow_guest_purchase>
      <allow_backorders>1</allow_backorders>
      <manufacturer></manufacturer>
      <c4_sysid>1222831</c4_sysid>
      <qty_increments>0.000000</qty_increments>
      <updated_at>2021-01-07T19:01:21.799000</updated_at>
      <dangerous_goods>0</dangerous_goods>
      <competitor_references>&quot;&quot;</competitor_references>
      <supplier>887</supplier>
      <visibility>both</visibility>
    </attributes>
    <attributes store="01">
      <allow_purchase>1</allow_purchase>
      <allow_guest_purchase>1</allow_guest_purchase>
      <visibility>both</visibility>
    </attributes>
    <attributes store="02">
      <allow_purchase>1</allow_purchase>
      <price>7859.000000</price>
      <visibility>both</visibility>
    </attributes>
    <attributes store="66">
      <allow_purchase>1</allow_purchase>
      <visibility>both</visibility>
    </attributes>
    <links>
      <link type="relation"/>
    </links>
    <type>simple</type>
  </product>
  <product>
    <sku>EL472545</sku>
    <name>SÅLLAXEL, GROV, HÖGRE</name>
    <status>enabled</status>
    <attributes store="admin">
      <status>1</status>
      <c4_status>5</c4_status>
      <m3_status>20</m3_status>
      <is_returnable>0</is_returnable>
      <allow_purchase>1</allow_purchase>
      <allow_guest_purchase>1</allow_guest_purchase>
      <allow_backorders>1</allow_backorders>
      <manufacturer></manufacturer>
      <c4_sysid>1208974</c4_sysid>
      <qty_increments>0.000000</qty_increments>
      <ean_number>7322236015058</ean_number>
      <updated_at>2021-01-07T19:01:21.939000</updated_at>
      <dangerous_goods>0</dangerous_goods>
      <competitor_references>&quot;&quot;</competitor_references>
      <supplier>887</supplier>
      <visibility>both</visibility>
    </attributes>
    <attributes store="01">
      <allow_purchase>1</allow_purchase>
      <allow_guest_purchase>1</allow_guest_purchase>
      <visibility>both</visibility>
    </attributes>
    <attributes store="02">
      <allow_purchase>1</allow_purchase>
      <price>4372.000000</price>
      <visibility>both</visibility>
    </attributes>
    <attributes store="66">
      <allow_purchase>1</allow_purchase>
      <visibility>both</visibility>
    </attributes>
    <links>
      <link type="relation"/>
    </links>
    <type>simple</type>
  </product>
</integrationbase>