<?xml version="1.0" encoding="utf-8"?>
<integrationbase>
  <product>
    <sku>VOE14572052</sku>
    <name>ROD</name>
    <status>enabled</status>
    <attributes store="admin">
      <status>1</status>
      <c4_status>8</c4_status>
      <m3_status>20</m3_status>
      <is_returnable>0</is_returnable>
      <allow_purchase>1</allow_purchase>
      <allow_guest_purchase>1</allow_guest_purchase>
      <allow_backorders>1</allow_backorders>
      <manufacturer></manufacturer>
      <c4_sysid>723746</c4_sysid>
      <replaces>&quot;VOE14550735&quot;</replaces>
      <updated_at>2021-01-18T10:45:33.757000</updated_at>
      <dangerous_goods>0</dangerous_goods>
      <competitor_references>&quot;&quot;</competitor_references>
      <supplier>001</supplier>
      <visibility>both</visibility>
    </attributes>
    <attributes store="01">
      <allow_purchase>0</allow_purchase>
      <allow_guest_purchase>0</allow_guest_purchase>
      <price>45592.000000</price>
      <visibility>none</visibility>
    </attributes>
    <attributes store="02">
      <allow_purchase>0</allow_purchase>
      <visibility>none</visibility>
    </attributes>
    <attributes store="66">
      <allow_purchase>0</allow_purchase>
      <visibility>none</visibility>
    </attributes>
    <links>
      <link type="relation"/>
    </links>
    <type>simple</type>
  </product>
  <product>
    <sku>VOE15068548</sku>
    <name>KOLVTÄTNING</name>
    <status>enabled</status>
    <attributes store="admin">
      <status>1</status>
      <c4_status>8</c4_status>
      <m3_status>20</m3_status>
      <is_returnable>0</is_returnable>
      <allow_purchase>1</allow_purchase>
      <allow_guest_purchase>1</allow_guest_purchase>
      <allow_backorders>1</allow_backorders>
      <manufacturer></manufacturer>
      <c4_sysid>726014</c4_sysid>
      <replaces>&quot;VOE11709874&quot;</replaces>
      <updated_at>2021-01-18T10:45:33.882000</updated_at>
      <dangerous_goods>0</dangerous_goods>
      <competitor_references>&quot;&quot;</competitor_references>
      <supplier>001</supplier>
      <visibility>both</visibility>
    </attributes>
    <attributes store="01">
      <allow_purchase>0</allow_purchase>
      <allow_guest_purchase>0</allow_guest_purchase>
      <price>4009.000000</price>
      <visibility>none</visibility>
    </attributes>
    <attributes store="02">
      <allow_purchase>0</allow_purchase>
      <visibility>none</visibility>
    </attributes>
    <attributes store="66">
      <allow_purchase>0</allow_purchase>
      <visibility>none</visibility>
    </attributes>
    <links>
      <link type="relation"/>
    </links>
    <type>simple</type>
  </product>
  <product>
    <sku>VOE14541935</sku>
    <name>Tapp</name>
    <status>enabled</status>
    <attributes store="admin">
      <status>1</status>
      <c4_status>8</c4_status>
      <m3_status>20</m3_status>
      <is_returnable>0</is_returnable>
      <allow_purchase>1</allow_purchase>
      <allow_guest_purchase>1</allow_guest_purchase>
      <allow_backorders>1</allow_backorders>
      <manufacturer></manufacturer>
      <c4_sysid>725084</c4_sysid>
      <replaces>&quot;VOE14510439&quot;</replaces>
      <updated_at>2021-01-18T10:45:34.038000</updated_at>
      <dangerous_goods>0</dangerous_goods>
      <competitor_references>&quot;&quot;</competitor_references>
      <supplier>001</supplier>
      <visibility>both</visibility>
    </attributes>
    <attributes store="01">
      <allow_purchase>0</allow_purchase>
      <allow_guest_purchase>0</allow_guest_purchase>
      <price>7944.000000</price>
      <visibility>none</visibility>
    </attributes>
    <attributes store="02">
      <allow_purchase>0</allow_purchase>
      <visibility>none</visibility>
    </attributes>
    <attributes store="66">
      <allow_purchase>0</allow_purchase>
      <visibility>none</visibility>
    </attributes>
    <links>
      <link type="relation"/>
    </links>
    <type>simple</type>
  </product>
  <product>
    <sku>VOE14599067</sku>
    <name>WIRE HARNESS</name>
    <status>enabled</status>
    <attributes store="admin">
      <status>1</status>
      <c4_status>8</c4_status>
      <m3_status>20</m3_status>
      <is_returnable>0</is_returnable>
      <allow_purchase>1</allow_purchase>
      <allow_guest_purchase>1</allow_guest_purchase>
      <allow_backorders>1</allow_backorders>
      <manufacturer></manufacturer>
      <c4_sysid>724828</c4_sysid>
      <ean_number>7322235415071</ean_number>
      <updated_at>2021-01-18T10:45:34.163000</updated_at>
      <dangerous_goods>0</dangerous_goods>
      <competitor_references>&quot;&quot;</competitor_references>
      <supplier>001</supplier>
      <visibility>both</visibility>
    </attributes>
    <attributes store="01">
      <allow_purchase>0</allow_purchase>
      <allow_guest_purchase>0</allow_guest_purchase>
      <price>843.000000</price>
      <visibility>none</visibility>
    </attributes>
    <attributes store="02">
      <allow_purchase>0</allow_purchase>
      <visibility>none</visibility>
    </attributes>
    <attributes store="66">
      <allow_purchase>0</allow_purchase>
      <visibility>none</visibility>
    </attributes>
    <links>
      <link type="relation"/>
    </links>
    <type>simple</type>
  </product>
  <product>
    <sku>VOE14737473</sku>
    <name>PLUGG</name>
    <status>enabled</status>
    <attributes store="admin">
      <status>1</status>
      <c4_status>8</c4_status>
      <m3_status>20</m3_status>
      <is_returnable>0</is_returnable>
      <allow_purchase>1</allow_purchase>
      <allow_guest_purchase>1</allow_guest_purchase>
      <allow_backorders>1</allow_backorders>
      <manufacturer></manufacturer>
      <c4_sysid>1206640</c4_sysid>
      <ean_number>7322236011548</ean_number>
      <updated_at>2021-01-18T10:45:34.303000</updated_at>
      <dangerous_goods>0</dangerous_goods>
      <competitor_references>&quot;&quot;</competitor_references>
      <supplier>001</supplier>
      <visibility>both</visibility>
    </attributes>
    <attributes store="01">
      <allow_purchase>0</allow_purchase>
      <allow_guest_purchase>0</allow_guest_purchase>
      <price>66.000000</price>
      <visibility>none</visibility>
    </attributes>
    <attributes store="02">
      <allow_purchase>0</allow_purchase>
      <visibility>none</visibility>
    </attributes>
    <attributes store="66">
      <allow_purchase>0</allow_purchase>
      <visibility>none</visibility>
    </attributes>
    <links>
      <link type="relation"/>
    </links>
    <type>simple</type>
  </product>
  <product>
    <sku>VOE14552683</sku>
    <name>PLATTA</name>
    <status>enabled</status>
    <attributes store="admin">
      <status>1</status>
      <c4_status>8</c4_status>
      <m3_status>20</m3_status>
      <is_returnable>0</is_returnable>
      <allow_purchase>1</allow_purchase>
      <allow_guest_purchase>1</allow_guest_purchase>
      <allow_backorders>1</allow_backorders>
      <manufacturer></manufacturer>
      <c4_sysid>728597</c4_sysid>
      <updated_at>2021-01-18T10:45:34.460000</updated_at>
      <dangerous_goods>0</dangerous_goods>
      <competitor_references>&quot;&quot;</competitor_references>
      <supplier>001</supplier>
      <visibility>both</visibility>
    </attributes>
    <attributes store="01">
      <allow_purchase>0</allow_purchase>
      <allow_guest_purchase>0</allow_guest_purchase>
      <price>366.000000</price>
      <visibility>none</visibility>
    </attributes>
    <attributes store="02">
      <allow_purchase>0</allow_purchase>
      <visibility>none</visibility>
    </attributes>
    <attributes store="66">
      <allow_purchase>0</allow_purchase>
      <visibility>none</visibility>
    </attributes>
    <links>
      <link type="relation"/>
    </links>
    <type>simple</type>
  </product>
  <product>
    <sku>VOE1501520</sku>
    <name>SKRUV</name>
    <status>enabled</status>
    <attributes store="admin">
      <status>1</status>
      <c4_status>8</c4_status>
      <m3_status>20</m3_status>
      <is_returnable>0</is_returnable>
      <allow_purchase>1</allow_purchase>
      <allow_guest_purchase>1</allow_guest_purchase>
      <allow_backorders>1</allow_backorders>
      <manufacturer></manufacturer>
      <c4_sysid>725445</c4_sysid>
      <updated_at>2021-01-18T10:45:34.585000</updated_at>
      <dangerous_goods>0</dangerous_goods>
      <competitor_references>&quot;&quot;</competitor_references>
      <supplier>001</supplier>
      <visibility>both</visibility>
    </attributes>
    <attributes store="01">
      <allow_purchase>0</allow_purchase>
      <allow_guest_purchase>0</allow_guest_purchase>
      <price>30.000000</price>
      <visibility>none</visibility>
    </attributes>
    <attributes store="02">
      <allow_purchase>0</allow_purchase>
      <visibility>none</visibility>
    </attributes>
    <attributes store="66">
      <allow_purchase>0</allow_purchase>
      <visibility>none</visibility>
    </attributes>
    <links>
      <link type="relation"/>
    </links>
    <type>simple</type>
  </product>
  <product>
    <sku>VOE14550595</sku>
    <name>IDLER (SPU)</name>
    <status>enabled</status>
    <attributes store="admin">
      <status>1</status>
      <c4_status>8</c4_status>
      <m3_status>20</m3_status>
      <is_returnable>0</is_returnable>
      <allow_purchase>1</allow_purchase>
      <allow_guest_purchase>1</allow_guest_purchase>
      <allow_backorders>1</allow_backorders>
      <manufacturer></manufacturer>
      <c4_sysid>725660</c4_sysid>
      <ean_number>7322235251754</ean_number>
      <updated_at>2021-01-18T10:45:34.694000</updated_at>
      <dangerous_goods>0</dangerous_goods>
      <competitor_references>&quot;&quot;</competitor_references>
      <supplier>001</supplier>
      <visibility>both</visibility>
    </attributes>
    <attributes store="01">
      <allow_purchase>0</allow_purchase>
      <allow_guest_purchase>0</allow_guest_purchase>
      <price>4757.000000</price>
      <visibility>none</visibility>
    </attributes>
    <attributes store="02">
      <allow_purchase>0</allow_purchase>
      <visibility>none</visibility>
    </attributes>
    <attributes store="66">
      <allow_purchase>0</allow_purchase>
      <visibility>none</visibility>
    </attributes>
    <links>
      <link type="relation"/>
    </links>
    <type>simple</type>
  </product>
  <product>
    <sku>VOE15071993</sku>
    <name>PLUG</name>
    <status>enabled</status>
    <attributes store="admin">
      <status>1</status>
      <c4_status>8</c4_status>
      <m3_status>20</m3_status>
      <is_returnable>0</is_returnable>
      <allow_purchase>1</allow_purchase>
      <allow_guest_purchase>1</allow_guest_purchase>
      <allow_backorders>1</allow_backorders>
      <manufacturer></manufacturer>
      <c4_sysid>729645</c4_sysid>
      <ean_number>7322235794213</ean_number>
      <updated_at>2021-01-18T10:45:34.819000</updated_at>
      <dangerous_goods>0</dangerous_goods>
      <competitor_references>&quot;&quot;</competitor_references>
      <supplier>001</supplier>
      <visibility>both</visibility>
    </attributes>
    <attributes store="01">
      <allow_purchase>0</allow_purchase>
      <allow_guest_purchase>0</allow_guest_purchase>
      <price>87.000000</price>
      <visibility>none</visibility>
    </attributes>
    <attributes store="02">
      <allow_purchase>0</allow_purchase>
      <visibility>none</visibility>
    </attributes>
    <attributes store="66">
      <allow_purchase>0</allow_purchase>
      <visibility>none</visibility>
    </attributes>
    <links>
      <link type="relation"/>
    </links>
    <type>simple</type>
  </product>
  <product>
    <sku>VOE14589121</sku>
    <name>SEALING KIT</name>
    <status>enabled</status>
    <attributes store="admin">
      <status>1</status>
      <c4_status>8</c4_status>
      <m3_status>20</m3_status>
      <is_returnable>0</is_returnable>
      <allow_purchase>1</allow_purchase>
      <allow_guest_purchase>1</allow_guest_purchase>
      <allow_backorders>1</allow_backorders>
      <manufacturer></manufacturer>
      <c4_sysid>726560</c4_sysid>
      <ean_number>7322235803755</ean_number>
      <updated_at>2021-01-18T10:45:34.944000</updated_at>
      <dangerous_goods>0</dangerous_goods>
      <competitor_references>&quot;&quot;</competitor_references>
      <supplier>001</supplier>
      <visibility>both</visibility>
    </attributes>
    <attributes store="01">
      <allow_purchase>0</allow_purchase>
      <allow_guest_purchase>0</allow_guest_purchase>
      <price>2594.000000</price>
      <visibility>none</visibility>
    </attributes>
    <attributes store="02">
      <allow_purchase>0</allow_purchase>
      <visibility>none</visibility>
    </attributes>
    <attributes store="66">
      <allow_purchase>0</allow_purchase>
      <visibility>none</visibility>
    </attributes>
    <links>
      <link type="relation"/>
    </links>
    <type>simple</type>
  </product>
  <product>
    <sku>VOE14578590</sku>
    <name>RÖR</name>
    <status>enabled</status>
    <attributes store="admin">
      <status>1</status>
      <c4_status>8</c4_status>
      <m3_status>20</m3_status>
      <is_returnable>0</is_returnable>
      <allow_purchase>1</allow_purchase>
      <allow_guest_purchase>1</allow_guest_purchase>
      <allow_backorders>1</allow_backorders>
      <manufacturer></manufacturer>
      <c4_sysid>726988</c4_sysid>
      <ean_number>7322235098656</ean_number>
      <updated_at>2021-01-18T10:45:35.085000</updated_at>
      <dangerous_goods>0</dangerous_goods>
      <competitor_references>&quot;&quot;</competitor_references>
      <supplier>001</supplier>
      <visibility>both</visibility>
    </attributes>
    <attributes store="01">
      <allow_purchase>0</allow_purchase>
      <allow_guest_purchase>0</allow_guest_purchase>
      <price>7247.000000</price>
      <visibility>none</visibility>
    </attributes>
    <attributes store="02">
      <allow_purchase>0</allow_purchase>
      <visibility>none</visibility>
    </attributes>
    <attributes store="66">
      <allow_purchase>0</allow_purchase>
      <visibility>none</visibility>
    </attributes>
    <links>
      <link type="relation"/>
    </links>
    <type>simple</type>
  </product>
  <product>
    <sku>VOE14643925</sku>
    <name>SWITCH</name>
    <status>enabled</status>
    <attributes store="admin">
      <status>1</status>
      <c4_status>8</c4_status>
      <m3_status>20</m3_status>
      <is_returnable>0</is_returnable>
      <allow_purchase>1</allow_purchase>
      <allow_guest_purchase>1</allow_guest_purchase>
      <allow_backorders>1</allow_backorders>
      <manufacturer></manufacturer>
      <c4_sysid>724931</c4_sysid>
      <ean_number>7322235562140</ean_number>
      <updated_at>2021-01-18T10:45:35.210000</updated_at>
      <dangerous_goods>0</dangerous_goods>
      <competitor_references>&quot;&quot;</competitor_references>
      <supplier>001</supplier>
      <visibility>both</visibility>
    </attributes>
    <attributes store="01">
      <allow_purchase>0</allow_purchase>
      <allow_guest_purchase>0</allow_guest_purchase>
      <price>1410.000000</price>
      <visibility>none</visibility>
    </attributes>
    <attributes store="02">
      <allow_purchase>0</allow_purchase>
      <visibility>none</visibility>
    </attributes>
    <attributes store="66">
      <allow_purchase>0</allow_purchase>
      <visibility>none</visibility>
    </attributes>
    <links>
      <link type="relation"/>
    </links>
    <type>simple</type>
  </product>
  <product>
    <sku>VOE15061045</sku>
    <name>VIPPARM</name>
    <status>enabled</status>
    <attributes store="admin">
      <status>1</status>
      <c4_status>8</c4_status>
      <m3_status>20</m3_status>
      <is_returnable>0</is_returnable>
      <allow_purchase>1</allow_purchase>
      <allow_guest_purchase>1</allow_guest_purchase>
      <allow_backorders>1</allow_backorders>
      <manufacturer></manufacturer>
      <c4_sysid>1490207</c4_sysid>
      <ean_number>7322236176964</ean_number>
      <updated_at>2021-01-18T10:45:35.335000</updated_at>
      <dangerous_goods>0</dangerous_goods>
      <competitor_references>&quot;&quot;</competitor_references>
      <supplier>001</supplier>
      <visibility>both</visibility>
    </attributes>
    <attributes store="01">
      <allow_purchase>0</allow_purchase>
      <allow_guest_purchase>0</allow_guest_purchase>
      <price>80.000000</price>
      <visibility>none</visibility>
    </attributes>
    <attributes store="02">
      <allow_purchase>0</allow_purchase>
      <visibility>none</visibility>
    </attributes>
    <attributes store="66">
      <allow_purchase>0</allow_purchase>
      <visibility>none</visibility>
    </attributes>
    <links>
      <link type="relation"/>
    </links>
    <type>simple</type>
  </product>
  <product>
    <sku>VOE14563334</sku>
    <name>SWING GEAR</name>
    <status>enabled</status>
    <attributes store="admin">
      <status>1</status>
      <c4_status>8</c4_status>
      <m3_status>20</m3_status>
      <is_returnable>0</is_returnable>
      <allow_purchase>1</allow_purchase>
      <allow_guest_purchase>1</allow_guest_purchase>
      <allow_backorders>1</allow_backorders>
      <manufacturer></manufacturer>
      <c4_sysid>729165</c4_sysid>
      <replaces>&quot;VOE14563344&quot;</replaces>
      <updated_at>2021-01-18T10:45:35.475000</updated_at>
      <dangerous_goods>0</dangerous_goods>
      <competitor_references>&quot;&quot;</competitor_references>
      <supplier>001</supplier>
      <visibility>both</visibility>
    </attributes>
    <attributes store="01">
      <allow_purchase>0</allow_purchase>
      <allow_guest_purchase>0</allow_guest_purchase>
      <price>93493.000000</price>
      <visibility>none</visibility>
    </attributes>
    <attributes store="02">
      <allow_purchase>0</allow_purchase>
      <visibility>none</visibility>
    </attributes>
    <attributes store="66">
      <allow_purchase>0</allow_purchase>
      <visibility>none</visibility>
    </attributes>
    <links>
      <link type="relation"/>
    </links>
    <type>simple</type>
  </product>
  <product>
    <sku>VOE14615234</sku>
    <name>PIN</name>
    <status>enabled</status>
    <attributes store="admin">
      <status>1</status>
      <c4_status>8</c4_status>
      <m3_status>20</m3_status>
      <is_returnable>0</is_returnable>
      <allow_purchase>1</allow_purchase>
      <allow_guest_purchase>1</allow_guest_purchase>
      <allow_backorders>1</allow_backorders>
      <manufacturer></manufacturer>
      <c4_sysid>686725</c4_sysid>
      <replaces>&quot;VOE14534184&quot;</replaces>
      <updated_at>2021-01-18T10:45:35.585000</updated_at>
      <dangerous_goods>0</dangerous_goods>
      <competitor_references>&quot;&quot;</competitor_references>
      <supplier>001</supplier>
      <visibility>both</visibility>
    </attributes>
    <attributes store="01">
      <allow_purchase>0</allow_purchase>
      <allow_guest_purchase>0</allow_guest_purchase>
      <price>873.000000</price>
      <visibility>none</visibility>
    </attributes>
    <attributes store="02">
      <allow_purchase>0</allow_purchase>
      <visibility>none</visibility>
    </attributes>
    <attributes store="66">
      <allow_purchase>0</allow_purchase>
      <visibility>none</visibility>
    </attributes>
    <links>
      <link type="relation"/>
    </links>
    <type>simple</type>
  </product>
  <product>
    <sku>VOE14709898</sku>
    <name>DRIVENHET</name>
    <status>disabled</status>
    <attributes store="admin">
      <status>0</status>
      <c4_status>2</c4_status>
      <m3_status>20</m3_status>
      <is_returnable>0</is_returnable>
      <allow_purchase>0</allow_purchase>
      <allow_guest_purchase>0</allow_guest_purchase>
      <allow_backorders>0</allow_backorders>
      <manufacturer></manufacturer>
      <c4_sysid>1086438</c4_sysid>
      <ean_number>7322236152838</ean_number>
      <updated_at>2021-01-18T10:45:35.725000</updated_at>
      <dangerous_goods>0</dangerous_goods>
      <competitor_references>&quot;&quot;</competitor_references>
      <supplier>001</supplier>
      <visibility>none</visibility>
    </attributes>
    <attributes store="01">
      <allow_purchase>0</allow_purchase>
      <allow_guest_purchase>0</allow_guest_purchase>
      <price>292814.000000</price>
      <visibility>none</visibility>
    </attributes>
    <attributes store="02">
      <allow_purchase>0</allow_purchase>
      <visibility>none</visibility>
    </attributes>
    <attributes store="66">
      <allow_purchase>0</allow_purchase>
      <visibility>none</visibility>
    </attributes>
    <links>
      <link type="relation"/>
    </links>
    <type>simple</type>
  </product>
  <product>
    <sku>VOE14690691</sku>
    <name>DECAL</name>
    <status>enabled</status>
    <attributes store="admin">
      <status>1</status>
      <c4_status>8</c4_status>
      <m3_status>20</m3_status>
      <is_returnable>0</is_returnable>
      <allow_purchase>1</allow_purchase>
      <allow_guest_purchase>1</allow_guest_purchase>
      <allow_backorders>1</allow_backorders>
      <manufacturer></manufacturer>
      <c4_sysid>724563</c4_sysid>
      <ean_number>7322235669542</ean_number>
      <updated_at>2021-01-18T10:45:35.850000</updated_at>
      <dangerous_goods>0</dangerous_goods>
      <competitor_references>&quot;&quot;</competitor_references>
      <supplier>001</supplier>
      <visibility>both</visibility>
    </attributes>
    <attributes store="01">
      <allow_purchase>0</allow_purchase>
      <allow_guest_purchase>0</allow_guest_purchase>
      <price>80.000000</price>
      <visibility>none</visibility>
    </attributes>
    <attributes store="02">
      <allow_purchase>0</allow_purchase>
      <visibility>none</visibility>
    </attributes>
    <attributes store="66">
      <allow_purchase>0</allow_purchase>
      <visibility>none</visibility>
    </attributes>
    <links>
      <link type="relation"/>
    </links>
    <type>simple</type>
  </product>
  <product>
    <sku>VOE14552387</sku>
    <name>VENTIL</name>
    <status>enabled</status>
    <attributes store="admin">
      <status>1</status>
      <c4_status>8</c4_status>
      <m3_status>20</m3_status>
      <is_returnable>0</is_returnable>
      <allow_purchase>1</allow_purchase>
      <allow_guest_purchase>1</allow_guest_purchase>
      <allow_backorders>1</allow_backorders>
      <manufacturer></manufacturer>
      <c4_sysid>729903</c4_sysid>
      <ean_number>7322234021167</ean_number>
      <updated_at>2021-01-18T10:45:35.991000</updated_at>
      <dangerous_goods>0</dangerous_goods>
      <competitor_references>&quot;&quot;</competitor_references>
      <supplier>001</supplier>
      <visibility>both</visibility>
    </attributes>
    <attributes store="01">
      <allow_purchase>0</allow_purchase>
      <allow_guest_purchase>0</allow_guest_purchase>
      <price>8446.000000</price>
      <visibility>none</visibility>
    </attributes>
    <attributes store="02">
      <allow_purchase>0</allow_purchase>
      <visibility>none</visibility>
    </attributes>
    <attributes store="66">
      <allow_purchase>0</allow_purchase>
      <visibility>none</visibility>
    </attributes>
    <links>
      <link type="relation"/>
    </links>
    <type>simple</type>
  </product>
  <product>
    <sku>VOE14556640</sku>
    <name>CLIP</name>
    <status>enabled</status>
    <attributes store="admin">
      <status>1</status>
      <c4_status>8</c4_status>
      <m3_status>20</m3_status>
      <is_returnable>0</is_returnable>
      <allow_purchase>1</allow_purchase>
      <allow_guest_purchase>1</allow_guest_purchase>
      <allow_backorders>1</allow_backorders>
      <manufacturer></manufacturer>
      <c4_sysid>1540608</c4_sysid>
      <ean_number>7322236178982</ean_number>
      <updated_at>2021-01-18T10:45:36.100000</updated_at>
      <dangerous_goods>0</dangerous_goods>
      <competitor_references>&quot;&quot;</competitor_references>
      <supplier>001</supplier>
      <visibility>both</visibility>
    </attributes>
    <attributes store="01">
      <allow_purchase>0</allow_purchase>
      <allow_guest_purchase>0</allow_guest_purchase>
      <price>37.000000</price>
      <visibility>none</visibility>
    </attributes>
    <attributes store="02">
      <allow_purchase>0</allow_purchase>
      <visibility>none</visibility>
    </attributes>
    <attributes store="66">
      <allow_purchase>0</allow_purchase>
      <visibility>none</visibility>
    </attributes>
    <links>
      <link type="relation"/>
    </links>
    <type>simple</type>
  </product>
  <product>
    <sku>VOE14606263</sku>
    <name>ACCUMULATOR</name>
    <status>enabled</status>
    <attributes store="admin">
      <status>1</status>
      <c4_status>8</c4_status>
      <m3_status>20</m3_status>
      <is_returnable>0</is_returnable>
      <allow_purchase>1</allow_purchase>
      <allow_guest_purchase>1</allow_guest_purchase>
      <allow_backorders>1</allow_backorders>
      <manufacturer></manufacturer>
      <c4_sysid>730386</c4_sysid>
      <replaces>&quot;VOE14588220&quot;</replaces>
      <updated_at>2021-01-18T10:45:36.210000</updated_at>
      <dangerous_goods>0</dangerous_goods>
      <competitor_references>&quot;&quot;</competitor_references>
      <supplier>001</supplier>
      <visibility>both</visibility>
    </attributes>
    <attributes store="01">
      <allow_purchase>0</allow_purchase>
      <allow_guest_purchase>0</allow_guest_purchase>
      <price>3720.000000</price>
      <visibility>none</visibility>
    </attributes>
    <attributes store="02">
      <allow_purchase>0</allow_purchase>
      <visibility>none</visibility>
    </attributes>
    <attributes store="66">
      <allow_purchase>0</allow_purchase>
      <visibility>none</visibility>
    </attributes>
    <links>
      <link type="relation"/>
    </links>
    <type>simple</type>
  </product>
  <product>
    <sku>VOE14685198</sku>
    <name>LINK</name>
    <status>enabled</status>
    <attributes store="admin">
      <status>1</status>
      <c4_status>8</c4_status>
      <m3_status>20</m3_status>
      <is_returnable>0</is_returnable>
      <allow_purchase>1</allow_purchase>
      <allow_guest_purchase>1</allow_guest_purchase>
      <allow_backorders>1</allow_backorders>
      <manufacturer></manufacturer>
      <c4_sysid>725476</c4_sysid>
      <ean_number>7322235801027</ean_number>
      <updated_at>2021-01-18T10:45:36.335000</updated_at>
      <dangerous_goods>0</dangerous_goods>
      <competitor_references>&quot;&quot;</competitor_references>
      <supplier>001</supplier>
      <visibility>both</visibility>
    </attributes>
    <attributes store="01">
      <allow_purchase>0</allow_purchase>
      <allow_guest_purchase>0</allow_guest_purchase>
      <price>3013.000000</price>
      <visibility>none</visibility>
    </attributes>
    <attributes store="02">
      <allow_purchase>0</allow_purchase>
      <visibility>none</visibility>
    </attributes>
    <attributes store="66">
      <allow_purchase>0</allow_purchase>
      <visibility>none</visibility>
    </attributes>
    <links>
      <link type="relation"/>
    </links>
    <type>simple</type>
  </product>
  <product>
    <sku>VOE14612947</sku>
    <name>KLAMMA</name>
    <status>enabled</status>
    <attributes store="admin">
      <status>1</status>
      <c4_status>8</c4_status>
      <m3_status>20</m3_status>
      <is_returnable>0</is_returnable>
      <allow_purchase>1</allow_purchase>
      <allow_guest_purchase>1</allow_guest_purchase>
      <allow_backorders>1</allow_backorders>
      <manufacturer></manufacturer>
      <c4_sysid>1480237</c4_sysid>
      <ean_number>7322236173420</ean_number>
      <updated_at>2021-01-18T10:45:36.444000</updated_at>
      <dangerous_goods>0</dangerous_goods>
      <competitor_references>&quot;&quot;</competitor_references>
      <supplier>001</supplier>
      <visibility>both</visibility>
    </attributes>
    <attributes store="01">
      <allow_purchase>0</allow_purchase>
      <allow_guest_purchase>0</allow_guest_purchase>
      <price>109.000000</price>
      <visibility>none</visibility>
    </attributes>
    <attributes store="02">
      <allow_purchase>0</allow_purchase>
      <visibility>none</visibility>
    </attributes>
    <attributes store="66">
      <allow_purchase>0</allow_purchase>
      <visibility>none</visibility>
    </attributes>
    <links>
      <link type="relation"/>
    </links>
    <type>simple</type>
  </product>
  <product>
    <sku>VOE14641505</sku>
    <name>CIGARETTE LIGHT</name>
    <status>enabled</status>
    <attributes store="admin">
      <status>1</status>
      <c4_status>8</c4_status>
      <m3_status>20</m3_status>
      <is_returnable>0</is_returnable>
      <allow_purchase>1</allow_purchase>
      <allow_guest_purchase>1</allow_guest_purchase>
      <allow_backorders>1</allow_backorders>
      <manufacturer></manufacturer>
      <c4_sysid>729913</c4_sysid>
      <ean_number>7322235677035</ean_number>
      <updated_at>2021-01-18T10:45:36.569000</updated_at>
      <dangerous_goods>0</dangerous_goods>
      <competitor_references>&quot;&quot;</competitor_references>
      <supplier>001</supplier>
      <visibility>both</visibility>
    </attributes>
    <attributes store="01">
      <allow_purchase>0</allow_purchase>
      <allow_guest_purchase>0</allow_guest_purchase>
      <price>526.000000</price>
      <visibility>none</visibility>
    </attributes>
    <attributes store="02">
      <allow_purchase>0</allow_purchase>
      <visibility>none</visibility>
    </attributes>
    <attributes store="66">
      <allow_purchase>0</allow_purchase>
      <visibility>none</visibility>
    </attributes>
    <links>
      <link type="relation"/>
    </links>
    <type>simple</type>
  </product>
  <product>
    <sku>VOE14698570</sku>
    <name>LOCKING DEVICE</name>
    <status>enabled</status>
    <attributes store="admin">
      <status>1</status>
      <c4_status>8</c4_status>
      <m3_status>20</m3_status>
      <is_returnable>0</is_returnable>
      <allow_purchase>1</allow_purchase>
      <allow_guest_purchase>1</allow_guest_purchase>
      <allow_backorders>1</allow_backorders>
      <manufacturer></manufacturer>
      <c4_sysid>1205382</c4_sysid>
      <ean_number>7322236028218</ean_number>
      <updated_at>2021-01-18T10:45:36.694000</updated_at>
      <dangerous_goods>0</dangerous_goods>
      <competitor_references>&quot;&quot;</competitor_references>
      <supplier>001</supplier>
      <visibility>both</visibility>
    </attributes>
    <attributes store="01">
      <allow_purchase>0</allow_purchase>
      <allow_guest_purchase>0</allow_guest_purchase>
      <price>457.000000</price>
      <visibility>none</visibility>
    </attributes>
    <attributes store="02">
      <allow_purchase>0</allow_purchase>
      <visibility>none</visibility>
    </attributes>
    <attributes store="66">
      <allow_purchase>0</allow_purchase>
      <visibility>none</visibility>
    </attributes>
    <links>
      <link type="relation"/>
    </links>
    <type>simple</type>
  </product>
  <product>
    <sku>VOE15037569</sku>
    <name>FEED LINE</name>
    <status>enabled</status>
    <attributes store="admin">
      <status>1</status>
      <c4_status>8</c4_status>
      <m3_status>20</m3_status>
      <is_returnable>0</is_returnable>
      <allow_purchase>1</allow_purchase>
      <allow_guest_purchase>1</allow_guest_purchase>
      <allow_backorders>1</allow_backorders>
      <manufacturer></manufacturer>
      <c4_sysid>725343</c4_sysid>
      <replaces>&quot;VOE11172762&quot;</replaces>
      <ean_number>7322234134188</ean_number>
      <updated_at>2021-01-18T10:45:36.819000</updated_at>
      <dangerous_goods>0</dangerous_goods>
      <competitor_references>&quot;&quot;</competitor_references>
      <supplier>001</supplier>
      <visibility>both</visibility>
    </attributes>
    <attributes store="01">
      <allow_purchase>0</allow_purchase>
      <allow_guest_purchase>0</allow_guest_purchase>
      <price>7237.000000</price>
      <visibility>none</visibility>
    </attributes>
    <attributes store="02">
      <allow_purchase>0</allow_purchase>
      <visibility>none</visibility>
    </attributes>
    <attributes store="66">
      <allow_purchase>0</allow_purchase>
      <visibility>none</visibility>
    </attributes>
    <links>
      <link type="relation"/>
    </links>
    <type>simple</type>
  </product>
  <product>
    <sku>VOE14881601</sku>
    <name>SLANGLEDNING</name>
    <status>enabled</status>
    <attributes store="admin">
      <status>1</status>
      <c4_status>8</c4_status>
      <m3_status>20</m3_status>
      <is_returnable>0</is_returnable>
      <allow_purchase>1</allow_purchase>
      <allow_guest_purchase>1</allow_guest_purchase>
      <allow_backorders>1</allow_backorders>
      <manufacturer></manufacturer>
      <c4_sysid>730099</c4_sysid>
      <ean_number>7322234530034</ean_number>
      <updated_at>2021-01-18T10:45:36.928000</updated_at>
      <dangerous_goods>0</dangerous_goods>
      <competitor_references>&quot;&quot;</competitor_references>
      <supplier>001</supplier>
      <visibility>both</visibility>
    </attributes>
    <attributes store="01">
      <allow_purchase>0</allow_purchase>
      <allow_guest_purchase>0</allow_guest_purchase>
      <price>2287.000000</price>
      <visibility>none</visibility>
    </attributes>
    <attributes store="02">
      <allow_purchase>0</allow_purchase>
      <visibility>none</visibility>
    </attributes>
    <attributes store="66">
      <allow_purchase>0</allow_purchase>
      <visibility>none</visibility>
    </attributes>
    <links>
      <link type="relation"/>
    </links>
    <type>simple</type>
  </product>
  <product>
    <sku>VOE14880923</sku>
    <name>SKRAPLIST</name>
    <status>enabled</status>
    <attributes store="admin">
      <status>1</status>
      <c4_status>8</c4_status>
      <m3_status>20</m3_status>
      <is_returnable>0</is_returnable>
      <allow_purchase>1</allow_purchase>
      <allow_guest_purchase>1</allow_guest_purchase>
      <allow_backorders>1</allow_backorders>
      <manufacturer></manufacturer>
      <c4_sysid>727731</c4_sysid>
      <ean_number>7322234532199</ean_number>
      <updated_at>2021-01-18T10:45:37.069000</updated_at>
      <dangerous_goods>0</dangerous_goods>
      <competitor_references>&quot;&quot;</competitor_references>
      <supplier>001</supplier>
      <visibility>both</visibility>
    </attributes>
    <attributes store="01">
      <allow_purchase>0</allow_purchase>
      <allow_guest_purchase>0</allow_guest_purchase>
      <price>169.000000</price>
      <visibility>none</visibility>
    </attributes>
    <attributes store="02">
      <allow_purchase>0</allow_purchase>
      <visibility>none</visibility>
    </attributes>
    <attributes store="66">
      <allow_purchase>0</allow_purchase>
      <visibility>none</visibility>
    </attributes>
    <links>
      <link type="relation"/>
    </links>
    <type>simple</type>
  </product>
  <product>
    <sku>VOE15015371</sku>
    <name>HOSE ASSEMBLY</name>
    <status>enabled</status>
    <attributes store="admin">
      <status>1</status>
      <c4_status>8</c4_status>
      <m3_status>20</m3_status>
      <is_returnable>0</is_returnable>
      <allow_purchase>1</allow_purchase>
      <allow_guest_purchase>1</allow_guest_purchase>
      <allow_backorders>1</allow_backorders>
      <manufacturer></manufacturer>
      <c4_sysid>729047</c4_sysid>
      <ean_number>7322235602051</ean_number>
      <updated_at>2021-01-18T10:45:37.178000</updated_at>
      <dangerous_goods>0</dangerous_goods>
      <competitor_references>&quot;&quot;</competitor_references>
      <supplier>001</supplier>
      <visibility>both</visibility>
    </attributes>
    <attributes store="01">
      <allow_purchase>0</allow_purchase>
      <allow_guest_purchase>0</allow_guest_purchase>
      <price>1606.000000</price>
      <visibility>none</visibility>
    </attributes>
    <attributes store="02">
      <allow_purchase>0</allow_purchase>
      <visibility>none</visibility>
    </attributes>
    <attributes store="66">
      <allow_purchase>0</allow_purchase>
      <visibility>none</visibility>
    </attributes>
    <links>
      <link type="relation"/>
    </links>
    <type>simple</type>
  </product>
  <product>
    <sku>VOE14657237</sku>
    <name>BRACKET</name>
    <status>enabled</status>
    <attributes store="admin">
      <status>1</status>
      <c4_status>8</c4_status>
      <m3_status>20</m3_status>
      <is_returnable>0</is_returnable>
      <allow_purchase>1</allow_purchase>
      <allow_guest_purchase>1</allow_guest_purchase>
      <allow_backorders>1</allow_backorders>
      <manufacturer></manufacturer>
      <c4_sysid>1178526</c4_sysid>
      <ean_number>7322236004205</ean_number>
      <updated_at>2021-01-18T10:45:37.288000</updated_at>
      <dangerous_goods>0</dangerous_goods>
      <competitor_references>&quot;&quot;</competitor_references>
      <supplier>001</supplier>
      <visibility>both</visibility>
    </attributes>
    <attributes store="01">
      <allow_purchase>0</allow_purchase>
      <allow_guest_purchase>0</allow_guest_purchase>
      <price>1112.000000</price>
      <visibility>none</visibility>
    </attributes>
    <attributes store="02">
      <allow_purchase>0</allow_purchase>
      <visibility>none</visibility>
    </attributes>
    <attributes store="66">
      <allow_purchase>0</allow_purchase>
      <visibility>none</visibility>
    </attributes>
    <links>
      <link type="relation"/>
    </links>
    <type>simple</type>
  </product>
  <product>
    <sku>VOE14659977</sku>
    <name>DECAL</name>
    <status>enabled</status>
    <attributes store="admin">
      <status>1</status>
      <c4_status>8</c4_status>
      <m3_status>20</m3_status>
      <is_returnable>0</is_returnable>
      <allow_purchase>1</allow_purchase>
      <allow_guest_purchase>1</allow_guest_purchase>
      <allow_backorders>1</allow_backorders>
      <manufacturer></manufacturer>
      <c4_sysid>725142</c4_sysid>
      <ean_number>7322235679961</ean_number>
      <updated_at>2021-01-18T10:45:37.397000</updated_at>
      <dangerous_goods>0</dangerous_goods>
      <competitor_references>&quot;&quot;</competitor_references>
      <supplier>001</supplier>
      <visibility>both</visibility>
    </attributes>
    <attributes store="01">
      <allow_purchase>0</allow_purchase>
      <allow_guest_purchase>0</allow_guest_purchase>
      <price>605.000000</price>
      <visibility>none</visibility>
    </attributes>
    <attributes store="02">
      <allow_purchase>0</allow_purchase>
      <visibility>none</visibility>
    </attributes>
    <attributes store="66">
      <allow_purchase>0</allow_purchase>
      <visibility>none</visibility>
    </attributes>
    <links>
      <link type="relation"/>
    </links>
    <type>simple</type>
  </product>
  <product>
    <sku>VOE14545571</sku>
    <name>RULLE</name>
    <status>enabled</status>
    <attributes store="admin">
      <status>1</status>
      <c4_status>8</c4_status>
      <m3_status>20</m3_status>
      <is_returnable>0</is_returnable>
      <allow_purchase>1</allow_purchase>
      <allow_guest_purchase>1</allow_guest_purchase>
      <allow_backorders>1</allow_backorders>
      <manufacturer></manufacturer>
      <c4_sysid>727987</c4_sysid>
      <replaces>&quot;VOE14528559&quot;</replaces>
      <updated_at>2021-01-18T10:45:37.507000</updated_at>
      <dangerous_goods>0</dangerous_goods>
      <competitor_references>&quot;&quot;</competitor_references>
      <supplier>001</supplier>
      <visibility>both</visibility>
    </attributes>
    <attributes store="01">
      <allow_purchase>0</allow_purchase>
      <allow_guest_purchase>0</allow_guest_purchase>
      <price>1285.000000</price>
      <visibility>none</visibility>
    </attributes>
    <attributes store="02">
      <allow_purchase>0</allow_purchase>
      <visibility>none</visibility>
    </attributes>
    <attributes store="66">
      <allow_purchase>0</allow_purchase>
      <visibility>none</visibility>
    </attributes>
    <links>
      <link type="relation"/>
    </links>
    <type>simple</type>
  </product>
  <product>
    <sku>VOE14556955</sku>
    <name>FUEL FILLING PU</name>
    <status>enabled</status>
    <attributes store="admin">
      <status>1</status>
      <c4_status>8</c4_status>
      <m3_status>20</m3_status>
      <is_returnable>0</is_returnable>
      <allow_purchase>1</allow_purchase>
      <allow_guest_purchase>1</allow_guest_purchase>
      <allow_backorders>1</allow_backorders>
      <manufacturer></manufacturer>
      <c4_sysid>724994</c4_sysid>
      <ean_number>7322234800762</ean_number>
      <updated_at>2021-01-18T10:45:37.616000</updated_at>
      <dangerous_goods>0</dangerous_goods>
      <competitor_references>&quot;&quot;</competitor_references>
      <supplier>001</supplier>
      <visibility>both</visibility>
    </attributes>
    <attributes store="01">
      <allow_purchase>0</allow_purchase>
      <allow_guest_purchase>0</allow_guest_purchase>
      <price>9002.000000</price>
      <visibility>none</visibility>
    </attributes>
    <attributes store="02">
      <allow_purchase>0</allow_purchase>
      <visibility>none</visibility>
    </attributes>
    <attributes store="66">
      <allow_purchase>0</allow_purchase>
      <visibility>none</visibility>
    </attributes>
    <links>
      <link type="relation"/>
    </links>
    <type>simple</type>
  </product>
  <product>
    <sku>VOE14698270</sku>
    <name>GRILLE</name>
    <status>enabled</status>
    <attributes store="admin">
      <status>1</status>
      <c4_status>8</c4_status>
      <m3_status>20</m3_status>
      <is_returnable>0</is_returnable>
      <allow_purchase>1</allow_purchase>
      <allow_guest_purchase>1</allow_guest_purchase>
      <allow_backorders>1</allow_backorders>
      <manufacturer></manufacturer>
      <c4_sysid>723705</c4_sysid>
      <replaces>&quot;VOE14660399&quot;</replaces>
      <updated_at>2021-01-18T10:45:37.741000</updated_at>
      <dangerous_goods>0</dangerous_goods>
      <competitor_references>&quot;&quot;</competitor_references>
      <supplier>001</supplier>
      <visibility>both</visibility>
    </attributes>
    <attributes store="01">
      <allow_purchase>0</allow_purchase>
      <allow_guest_purchase>0</allow_guest_purchase>
      <price>3581.000000</price>
      <visibility>none</visibility>
    </attributes>
    <attributes store="02">
      <allow_purchase>0</allow_purchase>
      <visibility>none</visibility>
    </attributes>
    <attributes store="66">
      <allow_purchase>0</allow_purchase>
      <visibility>none</visibility>
    </attributes>
    <links>
      <link type="relation"/>
    </links>
    <type>simple</type>
  </product>
  <product>
    <sku>VOE14722570</sku>
    <name>IDLER</name>
    <status>enabled</status>
    <attributes store="admin">
      <status>1</status>
      <c4_status>8</c4_status>
      <m3_status>20</m3_status>
      <is_returnable>0</is_returnable>
      <allow_purchase>1</allow_purchase>
      <allow_guest_purchase>1</allow_guest_purchase>
      <allow_backorders>1</allow_backorders>
      <manufacturer></manufacturer>
      <c4_sysid>726044</c4_sysid>
      <replaces>&quot;VOE14695200&quot;</replaces>
      <updated_at>2021-01-18T10:45:37.866000</updated_at>
      <dangerous_goods>0</dangerous_goods>
      <competitor_references>&quot;&quot;</competitor_references>
      <supplier>001</supplier>
      <visibility>both</visibility>
    </attributes>
    <attributes store="01">
      <allow_purchase>0</allow_purchase>
      <allow_guest_purchase>0</allow_guest_purchase>
      <price>6059.000000</price>
      <visibility>none</visibility>
    </attributes>
    <attributes store="02">
      <allow_purchase>0</allow_purchase>
      <visibility>none</visibility>
    </attributes>
    <attributes store="66">
      <allow_purchase>0</allow_purchase>
      <visibility>none</visibility>
    </attributes>
    <links>
      <link type="relation"/>
    </links>
    <type>simple</type>
  </product>
  <product>
    <sku>VOE14596338</sku>
    <name>SLANG</name>
    <status>enabled</status>
    <attributes store="admin">
      <status>1</status>
      <c4_status>8</c4_status>
      <m3_status>20</m3_status>
      <is_returnable>0</is_returnable>
      <allow_purchase>1</allow_purchase>
      <allow_guest_purchase>1</allow_guest_purchase>
      <allow_backorders>1</allow_backorders>
      <manufacturer></manufacturer>
      <c4_sysid>1197343</c4_sysid>
      <ean_number>7322235911887</ean_number>
      <updated_at>2021-01-18T10:45:37.991000</updated_at>
      <dangerous_goods>0</dangerous_goods>
      <competitor_references>&quot;&quot;</competitor_references>
      <supplier>001</supplier>
      <visibility>both</visibility>
    </attributes>
    <attributes store="01">
      <allow_purchase>0</allow_purchase>
      <allow_guest_purchase>0</allow_guest_purchase>
      <price>550.000000</price>
      <visibility>none</visibility>
    </attributes>
    <attributes store="02">
      <allow_purchase>0</allow_purchase>
      <visibility>none</visibility>
    </attributes>
    <attributes store="66">
      <allow_purchase>0</allow_purchase>
      <visibility>none</visibility>
    </attributes>
    <links>
      <link type="relation"/>
    </links>
    <type>simple</type>
  </product>
  <product>
    <sku>VOE15016390</sku>
    <name>DEKAL FLAK A35E</name>
    <status>enabled</status>
    <attributes store="admin">
      <status>1</status>
      <c4_status>8</c4_status>
      <m3_status>20</m3_status>
      <is_returnable>0</is_returnable>
      <allow_purchase>1</allow_purchase>
      <allow_guest_purchase>1</allow_guest_purchase>
      <allow_backorders>1</allow_backorders>
      <manufacturer></manufacturer>
      <c4_sysid>724173</c4_sysid>
      <replaces>&quot;VOE11116298&quot;</replaces>
      <ean_number>7322234158474</ean_number>
      <updated_at>2021-01-18T10:45:38.100000</updated_at>
      <dangerous_goods>0</dangerous_goods>
      <competitor_references>&quot;&quot;</competitor_references>
      <supplier>001</supplier>
      <visibility>both</visibility>
    </attributes>
    <attributes store="01">
      <allow_purchase>0</allow_purchase>
      <allow_guest_purchase>0</allow_guest_purchase>
      <price>736.000000</price>
      <visibility>none</visibility>
    </attributes>
    <attributes store="02">
      <allow_purchase>0</allow_purchase>
      <visibility>none</visibility>
    </attributes>
    <attributes store="66">
      <allow_purchase>0</allow_purchase>
      <visibility>none</visibility>
    </attributes>
    <links>
      <link type="relation"/>
    </links>
    <type>simple</type>
  </product>
  <product>
    <sku>VOE14699690</sku>
    <name>BLOCK</name>
    <status>enabled</status>
    <attributes store="admin">
      <status>1</status>
      <c4_status>8</c4_status>
      <m3_status>20</m3_status>
      <is_returnable>0</is_returnable>
      <allow_purchase>1</allow_purchase>
      <allow_guest_purchase>1</allow_guest_purchase>
      <allow_backorders>1</allow_backorders>
      <manufacturer></manufacturer>
      <c4_sysid>723781</c4_sysid>
      <ean_number>7322235565271</ean_number>
      <updated_at>2021-01-18T10:45:38.257000</updated_at>
      <dangerous_goods>0</dangerous_goods>
      <competitor_references>&quot;&quot;</competitor_references>
      <supplier>001</supplier>
      <visibility>both</visibility>
    </attributes>
    <attributes store="01">
      <allow_purchase>0</allow_purchase>
      <allow_guest_purchase>0</allow_guest_purchase>
      <price>1374.000000</price>
      <visibility>none</visibility>
    </attributes>
    <attributes store="02">
      <allow_purchase>0</allow_purchase>
      <visibility>none</visibility>
    </attributes>
    <attributes store="66">
      <allow_purchase>0</allow_purchase>
      <visibility>none</visibility>
    </attributes>
    <links>
      <link type="relation"/>
    </links>
    <type>simple</type>
  </product>
  <product>
    <sku>VOE14556940</sku>
    <name>SLANG</name>
    <status>enabled</status>
    <attributes store="admin">
      <status>1</status>
      <c4_status>8</c4_status>
      <m3_status>20</m3_status>
      <is_returnable>0</is_returnable>
      <allow_purchase>1</allow_purchase>
      <allow_guest_purchase>1</allow_guest_purchase>
      <allow_backorders>1</allow_backorders>
      <manufacturer></manufacturer>
      <c4_sysid>727719</c4_sysid>
      <ean_number>7322234618695</ean_number>
      <updated_at>2021-01-18T10:45:38.429000</updated_at>
      <dangerous_goods>0</dangerous_goods>
      <competitor_references>&quot;&quot;</competitor_references>
      <supplier>001</supplier>
      <visibility>both</visibility>
    </attributes>
    <attributes store="01">
      <allow_purchase>0</allow_purchase>
      <allow_guest_purchase>0</allow_guest_purchase>
      <price>1846.000000</price>
      <visibility>none</visibility>
    </attributes>
    <attributes store="02">
      <allow_purchase>0</allow_purchase>
      <visibility>none</visibility>
    </attributes>
    <attributes store="66">
      <allow_purchase>0</allow_purchase>
      <visibility>none</visibility>
    </attributes>
    <links>
      <link type="relation"/>
    </links>
    <type>simple</type>
  </product>
  <product>
    <sku>VOE14666321</sku>
    <name>DEKAL</name>
    <status>enabled</status>
    <attributes store="admin">
      <status>1</status>
      <c4_status>8</c4_status>
      <m3_status>20</m3_status>
      <is_returnable>0</is_returnable>
      <allow_purchase>1</allow_purchase>
      <allow_guest_purchase>1</allow_guest_purchase>
      <allow_backorders>1</allow_backorders>
      <manufacturer></manufacturer>
      <c4_sysid>724859</c4_sysid>
      <ean_number>7322235660679</ean_number>
      <updated_at>2021-01-18T10:45:38.601000</updated_at>
      <dangerous_goods>0</dangerous_goods>
      <competitor_references>&quot;&quot;</competitor_references>
      <supplier>001</supplier>
      <visibility>both</visibility>
    </attributes>
    <attributes store="01">
      <allow_purchase>0</allow_purchase>
      <allow_guest_purchase>0</allow_guest_purchase>
      <price>94.000000</price>
      <visibility>none</visibility>
    </attributes>
    <attributes store="02">
      <allow_purchase>0</allow_purchase>
      <visibility>none</visibility>
    </attributes>
    <attributes store="66">
      <allow_purchase>0</allow_purchase>
      <visibility>none</visibility>
    </attributes>
    <links>
      <link type="relation"/>
    </links>
    <type>simple</type>
  </product>
  <product>
    <sku>VOE14638537</sku>
    <name>SLANG</name>
    <status>enabled</status>
    <attributes store="admin">
      <status>1</status>
      <c4_status>8</c4_status>
      <m3_status>20</m3_status>
      <is_returnable>0</is_returnable>
      <allow_purchase>1</allow_purchase>
      <allow_guest_purchase>1</allow_guest_purchase>
      <allow_backorders>1</allow_backorders>
      <manufacturer></manufacturer>
      <c4_sysid>1194610</c4_sysid>
      <ean_number>7322236013085</ean_number>
      <updated_at>2021-01-18T10:45:38.757000</updated_at>
      <dangerous_goods>0</dangerous_goods>
      <competitor_references>&quot;&quot;</competitor_references>
      <supplier>001</supplier>
      <visibility>both</visibility>
    </attributes>
    <attributes store="01">
      <allow_purchase>0</allow_purchase>
      <allow_guest_purchase>0</allow_guest_purchase>
      <price>1833.000000</price>
      <visibility>none</visibility>
    </attributes>
    <attributes store="02">
      <allow_purchase>0</allow_purchase>
      <visibility>none</visibility>
    </attributes>
    <attributes store="66">
      <allow_purchase>0</allow_purchase>
      <visibility>none</visibility>
    </attributes>
    <links>
      <link type="relation"/>
    </links>
    <type>simple</type>
  </product>
</integrationbase>