<?xml version="1.0" encoding="utf-8"?>
<integrationbase>
  <product>
    <sku>VOE240059</sku>
    <name>BUSSNING</name>
    <status>enabled</status>
    <attributes store="admin">
      <status>1</status>
      <c4_status>8</c4_status>
      <m3_status>20</m3_status>
      <is_returnable>0</is_returnable>
      <allow_purchase>1</allow_purchase>
      <allow_guest_purchase>1</allow_guest_purchase>
      <allow_backorders>1</allow_backorders>
      <manufacturer></manufacturer>
      <c4_sysid>737949</c4_sysid>
      <replaces>&quot;VOE7240059&quot;</replaces>
      <updated_at>2021-01-18T10:53:35.615000</updated_at>
      <dangerous_goods>0</dangerous_goods>
      <competitor_references>&quot;&quot;</competitor_references>
      <supplier>001</supplier>
      <visibility>both</visibility>
    </attributes>
    <attributes store="01">
      <allow_purchase>0</allow_purchase>
      <allow_guest_purchase>0</allow_guest_purchase>
      <price>65.000000</price>
      <visibility>none</visibility>
    </attributes>
    <attributes store="02">
      <allow_purchase>0</allow_purchase>
      <visibility>none</visibility>
    </attributes>
    <attributes store="66">
      <allow_purchase>0</allow_purchase>
      <visibility>none</visibility>
    </attributes>
    <links>
      <link type="relation"/>
    </links>
    <type>simple</type>
  </product>
  <product>
    <sku>VOE16064843</sku>
    <name>FÄSTE</name>
    <status>enabled</status>
    <attributes store="admin">
      <status>1</status>
      <c4_status>8</c4_status>
      <m3_status>20</m3_status>
      <is_returnable>0</is_returnable>
      <allow_purchase>1</allow_purchase>
      <allow_guest_purchase>1</allow_guest_purchase>
      <allow_backorders>1</allow_backorders>
      <manufacturer></manufacturer>
      <c4_sysid>1202462</c4_sysid>
      <ean_number>7322236070842</ean_number>
      <updated_at>2021-01-18T10:53:35.755000</updated_at>
      <dangerous_goods>0</dangerous_goods>
      <competitor_references>&quot;&quot;</competitor_references>
      <supplier>001</supplier>
      <visibility>both</visibility>
    </attributes>
    <attributes store="01">
      <allow_purchase>0</allow_purchase>
      <allow_guest_purchase>0</allow_guest_purchase>
      <price>500.000000</price>
      <visibility>none</visibility>
    </attributes>
    <attributes store="02">
      <allow_purchase>0</allow_purchase>
      <visibility>none</visibility>
    </attributes>
    <attributes store="66">
      <allow_purchase>0</allow_purchase>
      <visibility>none</visibility>
    </attributes>
    <links>
      <link type="relation"/>
    </links>
    <type>simple</type>
  </product>
  <product>
    <sku>VOE17412190</sku>
    <name>CABLE HARNESS</name>
    <status>enabled</status>
    <attributes store="admin">
      <status>1</status>
      <c4_status>8</c4_status>
      <m3_status>20</m3_status>
      <is_returnable>0</is_returnable>
      <allow_purchase>1</allow_purchase>
      <allow_guest_purchase>1</allow_guest_purchase>
      <allow_backorders>1</allow_backorders>
      <manufacturer></manufacturer>
      <c4_sysid>1186974</c4_sysid>
      <ean_number>7322235982290</ean_number>
      <updated_at>2021-01-18T10:53:35.896000</updated_at>
      <dangerous_goods>0</dangerous_goods>
      <competitor_references>&quot;&quot;</competitor_references>
      <supplier>001</supplier>
      <visibility>both</visibility>
    </attributes>
    <attributes store="01">
      <allow_purchase>0</allow_purchase>
      <allow_guest_purchase>0</allow_guest_purchase>
      <price>16031.000000</price>
      <visibility>none</visibility>
    </attributes>
    <attributes store="02">
      <allow_purchase>0</allow_purchase>
      <visibility>none</visibility>
    </attributes>
    <attributes store="66">
      <allow_purchase>0</allow_purchase>
      <visibility>none</visibility>
    </attributes>
    <links>
      <link type="relation"/>
    </links>
    <type>simple</type>
  </product>
  <product>
    <sku>VOE4821057</sku>
    <name>PINNE</name>
    <status>enabled</status>
    <attributes store="admin">
      <status>1</status>
      <c4_status>8</c4_status>
      <m3_status>20</m3_status>
      <is_returnable>0</is_returnable>
      <allow_purchase>1</allow_purchase>
      <allow_guest_purchase>1</allow_guest_purchase>
      <allow_backorders>1</allow_backorders>
      <manufacturer></manufacturer>
      <c4_sysid>730710</c4_sysid>
      <updated_at>2021-01-18T10:53:36.037000</updated_at>
      <dangerous_goods>0</dangerous_goods>
      <competitor_references>&quot;&quot;</competitor_references>
      <supplier>001</supplier>
      <visibility>both</visibility>
    </attributes>
    <attributes store="01">
      <allow_purchase>0</allow_purchase>
      <allow_guest_purchase>0</allow_guest_purchase>
      <price>905.000000</price>
      <visibility>none</visibility>
    </attributes>
    <attributes store="02">
      <allow_purchase>0</allow_purchase>
      <visibility>none</visibility>
    </attributes>
    <attributes store="66">
      <allow_purchase>0</allow_purchase>
      <visibility>none</visibility>
    </attributes>
    <links>
      <link type="relation"/>
    </links>
    <type>simple</type>
  </product>
  <product>
    <sku>VOE20555343</sku>
    <name>KABEL</name>
    <status>enabled</status>
    <attributes store="admin">
      <status>1</status>
      <c4_status>8</c4_status>
      <m3_status>20</m3_status>
      <is_returnable>0</is_returnable>
      <allow_purchase>1</allow_purchase>
      <allow_guest_purchase>1</allow_guest_purchase>
      <allow_backorders>1</allow_backorders>
      <manufacturer></manufacturer>
      <c4_sysid>734463</c4_sysid>
      <updated_at>2021-01-18T10:53:36.162000</updated_at>
      <dangerous_goods>0</dangerous_goods>
      <competitor_references>&quot;&quot;</competitor_references>
      <supplier>001</supplier>
      <visibility>both</visibility>
    </attributes>
    <attributes store="01">
      <allow_purchase>0</allow_purchase>
      <allow_guest_purchase>0</allow_guest_purchase>
      <price>5937.000000</price>
      <visibility>none</visibility>
    </attributes>
    <attributes store="02">
      <allow_purchase>0</allow_purchase>
      <visibility>none</visibility>
    </attributes>
    <attributes store="66">
      <allow_purchase>0</allow_purchase>
      <visibility>none</visibility>
    </attributes>
    <links>
      <link type="relation"/>
    </links>
    <type>simple</type>
  </product>
  <product>
    <sku>VOE1650290</sku>
    <name>TÄTNINGSRING</name>
    <status>enabled</status>
    <attributes store="admin">
      <status>1</status>
      <c4_status>8</c4_status>
      <m3_status>20</m3_status>
      <is_returnable>0</is_returnable>
      <allow_purchase>1</allow_purchase>
      <allow_guest_purchase>1</allow_guest_purchase>
      <allow_backorders>1</allow_backorders>
      <manufacturer></manufacturer>
      <c4_sysid>738147</c4_sysid>
      <updated_at>2021-01-18T10:53:36.255000</updated_at>
      <dangerous_goods>0</dangerous_goods>
      <competitor_references>&quot;&quot;</competitor_references>
      <supplier>001</supplier>
      <visibility>both</visibility>
    </attributes>
    <attributes store="01">
      <allow_purchase>0</allow_purchase>
      <allow_guest_purchase>0</allow_guest_purchase>
      <price>475.000000</price>
      <visibility>none</visibility>
    </attributes>
    <attributes store="02">
      <allow_purchase>0</allow_purchase>
      <visibility>none</visibility>
    </attributes>
    <attributes store="66">
      <allow_purchase>0</allow_purchase>
      <visibility>none</visibility>
    </attributes>
    <links>
      <link type="relation"/>
    </links>
    <type>simple</type>
  </product>
  <product>
    <sku>VOE478896</sku>
    <name>HYLSA</name>
    <status>enabled</status>
    <attributes store="admin">
      <status>1</status>
      <c4_status>8</c4_status>
      <m3_status>20</m3_status>
      <is_returnable>0</is_returnable>
      <allow_purchase>1</allow_purchase>
      <allow_guest_purchase>1</allow_guest_purchase>
      <allow_backorders>1</allow_backorders>
      <manufacturer></manufacturer>
      <c4_sysid>734432</c4_sysid>
      <replaces>&quot;VOE471311&quot;</replaces>
      <updated_at>2021-01-18T10:53:36.380000</updated_at>
      <dangerous_goods>0</dangerous_goods>
      <competitor_references>&quot;&quot;</competitor_references>
      <supplier>001</supplier>
      <visibility>both</visibility>
    </attributes>
    <attributes store="01">
      <allow_purchase>0</allow_purchase>
      <allow_guest_purchase>0</allow_guest_purchase>
      <price>93.000000</price>
      <visibility>none</visibility>
    </attributes>
    <attributes store="02">
      <allow_purchase>0</allow_purchase>
      <visibility>none</visibility>
    </attributes>
    <attributes store="66">
      <allow_purchase>0</allow_purchase>
      <visibility>none</visibility>
    </attributes>
    <links>
      <link type="relation"/>
    </links>
    <type>simple</type>
  </product>
  <product>
    <sku>VOE4880972</sku>
    <name>AXIALBRICKA</name>
    <status>enabled</status>
    <attributes store="admin">
      <status>1</status>
      <c4_status>8</c4_status>
      <m3_status>20</m3_status>
      <is_returnable>0</is_returnable>
      <allow_purchase>1</allow_purchase>
      <allow_guest_purchase>1</allow_guest_purchase>
      <allow_backorders>1</allow_backorders>
      <manufacturer></manufacturer>
      <c4_sysid>735464</c4_sysid>
      <updated_at>2021-01-18T10:53:36.537000</updated_at>
      <dangerous_goods>0</dangerous_goods>
      <competitor_references>&quot;&quot;</competitor_references>
      <supplier>001</supplier>
      <visibility>both</visibility>
    </attributes>
    <attributes store="01">
      <allow_purchase>0</allow_purchase>
      <allow_guest_purchase>0</allow_guest_purchase>
      <price>271.000000</price>
      <visibility>none</visibility>
    </attributes>
    <attributes store="02">
      <allow_purchase>0</allow_purchase>
      <visibility>none</visibility>
    </attributes>
    <attributes store="66">
      <allow_purchase>0</allow_purchase>
      <visibility>none</visibility>
    </attributes>
    <links>
      <link type="relation"/>
    </links>
    <type>simple</type>
  </product>
  <product>
    <sku>VOE15216985</sku>
    <name>HOSE ASSEMBLY</name>
    <status>enabled</status>
    <attributes store="admin">
      <status>1</status>
      <c4_status>8</c4_status>
      <m3_status>20</m3_status>
      <is_returnable>0</is_returnable>
      <allow_purchase>1</allow_purchase>
      <allow_guest_purchase>1</allow_guest_purchase>
      <allow_backorders>1</allow_backorders>
      <manufacturer></manufacturer>
      <c4_sysid>725814</c4_sysid>
      <ean_number>7322235250726</ean_number>
      <updated_at>2021-01-18T10:53:36.662000</updated_at>
      <dangerous_goods>0</dangerous_goods>
      <competitor_references>&quot;&quot;</competitor_references>
      <supplier>001</supplier>
      <visibility>both</visibility>
    </attributes>
    <attributes store="01">
      <allow_purchase>0</allow_purchase>
      <allow_guest_purchase>0</allow_guest_purchase>
      <price>1807.000000</price>
      <visibility>none</visibility>
    </attributes>
    <attributes store="02">
      <allow_purchase>0</allow_purchase>
      <visibility>none</visibility>
    </attributes>
    <attributes store="66">
      <allow_purchase>0</allow_purchase>
      <visibility>none</visibility>
    </attributes>
    <links>
      <link type="relation"/>
    </links>
    <type>simple</type>
  </product>
  <product>
    <sku>VOE15205698</sku>
    <name>HUV</name>
    <status>enabled</status>
    <attributes store="admin">
      <status>1</status>
      <c4_status>8</c4_status>
      <m3_status>20</m3_status>
      <is_returnable>0</is_returnable>
      <allow_purchase>1</allow_purchase>
      <allow_guest_purchase>1</allow_guest_purchase>
      <allow_backorders>1</allow_backorders>
      <manufacturer></manufacturer>
      <c4_sysid>725680</c4_sysid>
      <ean_number>7322234375536</ean_number>
      <updated_at>2021-01-18T10:53:36.802000</updated_at>
      <dangerous_goods>0</dangerous_goods>
      <competitor_references>&quot;&quot;</competitor_references>
      <supplier>001</supplier>
      <visibility>both</visibility>
    </attributes>
    <attributes store="01">
      <allow_purchase>0</allow_purchase>
      <allow_guest_purchase>0</allow_guest_purchase>
      <price>33746.000000</price>
      <visibility>none</visibility>
    </attributes>
    <attributes store="02">
      <allow_purchase>0</allow_purchase>
      <visibility>none</visibility>
    </attributes>
    <attributes store="66">
      <allow_purchase>0</allow_purchase>
      <visibility>none</visibility>
    </attributes>
    <links>
      <link type="relation"/>
    </links>
    <type>simple</type>
  </product>
  <product>
    <sku>VOE4718008</sku>
    <name>BRICKA</name>
    <status>enabled</status>
    <attributes store="admin">
      <status>1</status>
      <c4_status>8</c4_status>
      <m3_status>20</m3_status>
      <is_returnable>0</is_returnable>
      <allow_purchase>1</allow_purchase>
      <allow_guest_purchase>1</allow_guest_purchase>
      <allow_backorders>1</allow_backorders>
      <manufacturer></manufacturer>
      <c4_sysid>733588</c4_sysid>
      <updated_at>2021-01-18T10:53:36.927000</updated_at>
      <dangerous_goods>0</dangerous_goods>
      <competitor_references>&quot;&quot;</competitor_references>
      <supplier>001</supplier>
      <visibility>both</visibility>
    </attributes>
    <attributes store="01">
      <allow_purchase>0</allow_purchase>
      <allow_guest_purchase>0</allow_guest_purchase>
      <price>502.000000</price>
      <visibility>none</visibility>
    </attributes>
    <attributes store="02">
      <allow_purchase>0</allow_purchase>
      <visibility>none</visibility>
    </attributes>
    <attributes store="66">
      <allow_purchase>0</allow_purchase>
      <visibility>none</visibility>
    </attributes>
    <links>
      <link type="relation"/>
    </links>
    <type>simple</type>
  </product>
  <product>
    <sku>VOE21915562</sku>
    <name>STÄNKSKYDD</name>
    <status>enabled</status>
    <attributes store="admin">
      <status>1</status>
      <c4_status>8</c4_status>
      <m3_status>20</m3_status>
      <is_returnable>0</is_returnable>
      <allow_purchase>1</allow_purchase>
      <allow_guest_purchase>1</allow_guest_purchase>
      <allow_backorders>1</allow_backorders>
      <manufacturer></manufacturer>
      <c4_sysid>1385405</c4_sysid>
      <ean_number>7322236164275</ean_number>
      <updated_at>2021-01-18T10:53:37.052000</updated_at>
      <dangerous_goods>0</dangerous_goods>
      <competitor_references>&quot;&quot;</competitor_references>
      <supplier>001</supplier>
      <visibility>both</visibility>
    </attributes>
    <attributes store="01">
      <allow_purchase>0</allow_purchase>
      <allow_guest_purchase>0</allow_guest_purchase>
      <price>431.000000</price>
      <visibility>none</visibility>
    </attributes>
    <attributes store="02">
      <allow_purchase>0</allow_purchase>
      <visibility>none</visibility>
    </attributes>
    <attributes store="66">
      <allow_purchase>0</allow_purchase>
      <visibility>none</visibility>
    </attributes>
    <links>
      <link type="relation"/>
    </links>
    <type>simple</type>
  </product>
  <product>
    <sku>VOE4898544</sku>
    <name>MUTTERPLATTA</name>
    <status>enabled</status>
    <attributes store="admin">
      <status>1</status>
      <c4_status>8</c4_status>
      <m3_status>20</m3_status>
      <is_returnable>0</is_returnable>
      <allow_purchase>1</allow_purchase>
      <allow_guest_purchase>1</allow_guest_purchase>
      <allow_backorders>1</allow_backorders>
      <manufacturer></manufacturer>
      <c4_sysid>737288</c4_sysid>
      <updated_at>2021-01-18T10:53:37.162000</updated_at>
      <dangerous_goods>0</dangerous_goods>
      <competitor_references>&quot;&quot;</competitor_references>
      <supplier>001</supplier>
      <visibility>both</visibility>
    </attributes>
    <attributes store="01">
      <allow_purchase>0</allow_purchase>
      <allow_guest_purchase>0</allow_guest_purchase>
      <price>789.000000</price>
      <visibility>none</visibility>
    </attributes>
    <attributes store="02">
      <allow_purchase>0</allow_purchase>
      <visibility>none</visibility>
    </attributes>
    <attributes store="66">
      <allow_purchase>0</allow_purchase>
      <visibility>none</visibility>
    </attributes>
    <links>
      <link type="relation"/>
    </links>
    <type>simple</type>
  </product>
  <product>
    <sku>VOE20405613</sku>
    <name>PACKNING</name>
    <status>enabled</status>
    <attributes store="admin">
      <status>1</status>
      <c4_status>8</c4_status>
      <m3_status>20</m3_status>
      <is_returnable>0</is_returnable>
      <allow_purchase>1</allow_purchase>
      <allow_guest_purchase>1</allow_guest_purchase>
      <allow_backorders>1</allow_backorders>
      <manufacturer></manufacturer>
      <c4_sysid>735471</c4_sysid>
      <updated_at>2021-01-18T10:53:37.287000</updated_at>
      <dangerous_goods>0</dangerous_goods>
      <competitor_references>&quot;&quot;</competitor_references>
      <supplier>001</supplier>
      <visibility>both</visibility>
    </attributes>
    <attributes store="01">
      <allow_purchase>0</allow_purchase>
      <allow_guest_purchase>0</allow_guest_purchase>
      <price>68.000000</price>
      <visibility>none</visibility>
    </attributes>
    <attributes store="02">
      <allow_purchase>0</allow_purchase>
      <visibility>none</visibility>
    </attributes>
    <attributes store="66">
      <allow_purchase>0</allow_purchase>
      <visibility>none</visibility>
    </attributes>
    <links>
      <link type="relation"/>
    </links>
    <type>simple</type>
  </product>
  <product>
    <sku>VOE15134495</sku>
    <name>SLANG</name>
    <status>enabled</status>
    <attributes store="admin">
      <status>1</status>
      <c4_status>8</c4_status>
      <m3_status>20</m3_status>
      <is_returnable>0</is_returnable>
      <allow_purchase>1</allow_purchase>
      <allow_guest_purchase>1</allow_guest_purchase>
      <allow_backorders>1</allow_backorders>
      <manufacturer></manufacturer>
      <c4_sysid>726111</c4_sysid>
      <ean_number>7322234528536</ean_number>
      <updated_at>2021-01-18T10:53:37.428000</updated_at>
      <dangerous_goods>0</dangerous_goods>
      <competitor_references>&quot;&quot;</competitor_references>
      <supplier>001</supplier>
      <visibility>both</visibility>
    </attributes>
    <attributes store="01">
      <allow_purchase>0</allow_purchase>
      <allow_guest_purchase>0</allow_guest_purchase>
      <price>2446.000000</price>
      <visibility>none</visibility>
    </attributes>
    <attributes store="02">
      <allow_purchase>0</allow_purchase>
      <visibility>none</visibility>
    </attributes>
    <attributes store="66">
      <allow_purchase>0</allow_purchase>
      <visibility>none</visibility>
    </attributes>
    <links>
      <link type="relation"/>
    </links>
    <type>simple</type>
  </product>
  <product>
    <sku>VOE20405888</sku>
    <name>GASKET</name>
    <status>enabled</status>
    <attributes store="admin">
      <status>1</status>
      <c4_status>8</c4_status>
      <m3_status>20</m3_status>
      <is_returnable>0</is_returnable>
      <allow_purchase>1</allow_purchase>
      <allow_guest_purchase>1</allow_guest_purchase>
      <allow_backorders>1</allow_backorders>
      <manufacturer></manufacturer>
      <c4_sysid>735560</c4_sysid>
      <replaces>&quot;VOE11700391&quot;,&quot;ZM 2900387&quot;</replaces>
      <updated_at>2021-01-18T10:53:37.553000</updated_at>
      <categories>1326389</categories>
      <dangerous_goods>0</dangerous_goods>
      <competitor_references>&quot;&quot;</competitor_references>
      <supplier>001</supplier>
      <visibility>both</visibility>
    </attributes>
    <attributes store="01">
      <allow_purchase>0</allow_purchase>
      <allow_guest_purchase>0</allow_guest_purchase>
      <price>22.000000</price>
      <visibility>none</visibility>
    </attributes>
    <attributes store="02">
      <allow_purchase>0</allow_purchase>
      <visibility>none</visibility>
    </attributes>
    <attributes store="66">
      <allow_purchase>0</allow_purchase>
      <visibility>none</visibility>
    </attributes>
    <links>
      <link type="relation"/>
    </links>
    <type>simple</type>
  </product>
  <product>
    <sku>VOE1578058</sku>
    <name>HUS</name>
    <status>enabled</status>
    <attributes store="admin">
      <status>1</status>
      <c4_status>8</c4_status>
      <m3_status>20</m3_status>
      <is_returnable>0</is_returnable>
      <allow_purchase>1</allow_purchase>
      <allow_guest_purchase>1</allow_guest_purchase>
      <allow_backorders>1</allow_backorders>
      <manufacturer></manufacturer>
      <c4_sysid>736840</c4_sysid>
      <updated_at>2021-01-18T10:53:37.694000</updated_at>
      <dangerous_goods>0</dangerous_goods>
      <competitor_references>&quot;&quot;</competitor_references>
      <supplier>001</supplier>
      <visibility>both</visibility>
    </attributes>
    <attributes store="01">
      <allow_purchase>0</allow_purchase>
      <allow_guest_purchase>0</allow_guest_purchase>
      <price>1033.000000</price>
      <visibility>none</visibility>
    </attributes>
    <attributes store="02">
      <allow_purchase>0</allow_purchase>
      <visibility>none</visibility>
    </attributes>
    <attributes store="66">
      <allow_purchase>0</allow_purchase>
      <visibility>none</visibility>
    </attributes>
    <links>
      <link type="relation"/>
    </links>
    <type>simple</type>
  </product>
  <product>
    <sku>VOE15116252</sku>
    <name>VALVE COVER</name>
    <status>enabled</status>
    <attributes store="admin">
      <status>1</status>
      <c4_status>8</c4_status>
      <m3_status>20</m3_status>
      <is_returnable>0</is_returnable>
      <allow_purchase>1</allow_purchase>
      <allow_guest_purchase>1</allow_guest_purchase>
      <allow_backorders>1</allow_backorders>
      <manufacturer></manufacturer>
      <c4_sysid>726082</c4_sysid>
      <replaces>&quot;VOE11118605&quot;</replaces>
      <updated_at>2021-01-18T10:53:37.819000</updated_at>
      <dangerous_goods>0</dangerous_goods>
      <competitor_references>&quot;&quot;</competitor_references>
      <supplier>001</supplier>
      <visibility>both</visibility>
    </attributes>
    <attributes store="01">
      <allow_purchase>0</allow_purchase>
      <allow_guest_purchase>0</allow_guest_purchase>
      <price>2685.000000</price>
      <visibility>none</visibility>
    </attributes>
    <attributes store="02">
      <allow_purchase>0</allow_purchase>
      <visibility>none</visibility>
    </attributes>
    <attributes store="66">
      <allow_purchase>0</allow_purchase>
      <visibility>none</visibility>
    </attributes>
    <links>
      <link type="relation"/>
    </links>
    <type>simple</type>
  </product>
  <product>
    <sku>VOE16821437</sku>
    <name>BATTERY BOX</name>
    <status>enabled</status>
    <attributes store="admin">
      <status>1</status>
      <c4_status>8</c4_status>
      <m3_status>20</m3_status>
      <is_returnable>0</is_returnable>
      <allow_purchase>1</allow_purchase>
      <allow_guest_purchase>1</allow_guest_purchase>
      <allow_backorders>1</allow_backorders>
      <manufacturer></manufacturer>
      <c4_sysid>737591</c4_sysid>
      <ean_number>7322235832090</ean_number>
      <updated_at>2021-01-18T10:53:37.928000</updated_at>
      <dangerous_goods>0</dangerous_goods>
      <competitor_references>&quot;&quot;</competitor_references>
      <supplier>001</supplier>
      <visibility>both</visibility>
    </attributes>
    <attributes store="01">
      <allow_purchase>0</allow_purchase>
      <allow_guest_purchase>0</allow_guest_purchase>
      <price>14175.000000</price>
      <visibility>none</visibility>
    </attributes>
    <attributes store="02">
      <allow_purchase>0</allow_purchase>
      <visibility>none</visibility>
    </attributes>
    <attributes store="66">
      <allow_purchase>0</allow_purchase>
      <visibility>none</visibility>
    </attributes>
    <links>
      <link type="relation"/>
    </links>
    <type>simple</type>
  </product>
  <product>
    <sku>VOE17464938</sku>
    <name>RÖR</name>
    <status>enabled</status>
    <attributes store="admin">
      <status>1</status>
      <c4_status>8</c4_status>
      <m3_status>20</m3_status>
      <is_returnable>0</is_returnable>
      <allow_purchase>1</allow_purchase>
      <allow_guest_purchase>1</allow_guest_purchase>
      <allow_backorders>1</allow_backorders>
      <manufacturer></manufacturer>
      <c4_sysid>733500</c4_sysid>
      <replaces>&quot;VOE15019937&quot;</replaces>
      <updated_at>2021-01-18T10:53:38.069000</updated_at>
      <dangerous_goods>0</dangerous_goods>
      <competitor_references>&quot;&quot;</competitor_references>
      <supplier>001</supplier>
      <visibility>both</visibility>
    </attributes>
    <attributes store="01">
      <allow_purchase>0</allow_purchase>
      <allow_guest_purchase>0</allow_guest_purchase>
      <price>1323.000000</price>
      <visibility>none</visibility>
    </attributes>
    <attributes store="02">
      <allow_purchase>0</allow_purchase>
      <visibility>none</visibility>
    </attributes>
    <attributes store="66">
      <allow_purchase>0</allow_purchase>
      <visibility>none</visibility>
    </attributes>
    <links>
      <link type="relation"/>
    </links>
    <type>simple</type>
  </product>
  <product>
    <sku>VOE4784695</sku>
    <name>KOLVSTÅNG</name>
    <status>enabled</status>
    <attributes store="admin">
      <status>1</status>
      <c4_status>8</c4_status>
      <m3_status>20</m3_status>
      <is_returnable>0</is_returnable>
      <allow_purchase>1</allow_purchase>
      <allow_guest_purchase>1</allow_guest_purchase>
      <allow_backorders>1</allow_backorders>
      <manufacturer></manufacturer>
      <c4_sysid>735323</c4_sysid>
      <updated_at>2021-01-18T10:53:38.194000</updated_at>
      <dangerous_goods>0</dangerous_goods>
      <competitor_references>&quot;&quot;</competitor_references>
      <supplier>001</supplier>
      <visibility>both</visibility>
    </attributes>
    <attributes store="01">
      <allow_purchase>0</allow_purchase>
      <allow_guest_purchase>0</allow_guest_purchase>
      <price>8670.000000</price>
      <visibility>none</visibility>
    </attributes>
    <attributes store="02">
      <allow_purchase>0</allow_purchase>
      <visibility>none</visibility>
    </attributes>
    <attributes store="66">
      <allow_purchase>0</allow_purchase>
      <visibility>none</visibility>
    </attributes>
    <links>
      <link type="relation"/>
    </links>
    <type>simple</type>
  </product>
  <product>
    <sku>VOE16213143</sku>
    <name>WINDOW</name>
    <status>enabled</status>
    <attributes store="admin">
      <status>1</status>
      <c4_status>8</c4_status>
      <m3_status>20</m3_status>
      <is_returnable>0</is_returnable>
      <allow_purchase>1</allow_purchase>
      <allow_guest_purchase>1</allow_guest_purchase>
      <allow_backorders>1</allow_backorders>
      <manufacturer></manufacturer>
      <c4_sysid>735216</c4_sysid>
      <ean_number>7322235695077</ean_number>
      <updated_at>2021-01-18T10:53:38.334000</updated_at>
      <dangerous_goods>0</dangerous_goods>
      <competitor_references>&quot;&quot;</competitor_references>
      <supplier>001</supplier>
      <visibility>both</visibility>
    </attributes>
    <attributes store="01">
      <allow_purchase>0</allow_purchase>
      <allow_guest_purchase>0</allow_guest_purchase>
      <price>6410.000000</price>
      <visibility>none</visibility>
    </attributes>
    <attributes store="02">
      <allow_purchase>0</allow_purchase>
      <visibility>none</visibility>
    </attributes>
    <attributes store="66">
      <allow_purchase>0</allow_purchase>
      <visibility>none</visibility>
    </attributes>
    <links>
      <link type="relation"/>
    </links>
    <type>simple</type>
  </product>
  <product>
    <sku>VOE17246170</sku>
    <name>GEAR RING</name>
    <status>enabled</status>
    <attributes store="admin">
      <status>1</status>
      <c4_status>8</c4_status>
      <m3_status>20</m3_status>
      <is_returnable>0</is_returnable>
      <allow_purchase>1</allow_purchase>
      <allow_guest_purchase>1</allow_guest_purchase>
      <allow_backorders>1</allow_backorders>
      <manufacturer></manufacturer>
      <c4_sysid>731827</c4_sysid>
      <replaces>&quot;VOE4717070&quot;</replaces>
      <updated_at>2021-01-18T10:53:38.459000</updated_at>
      <dangerous_goods>0</dangerous_goods>
      <competitor_references>&quot;&quot;</competitor_references>
      <supplier>001</supplier>
      <visibility>both</visibility>
    </attributes>
    <attributes store="01">
      <allow_purchase>0</allow_purchase>
      <allow_guest_purchase>0</allow_guest_purchase>
      <price>28018.000000</price>
      <visibility>none</visibility>
    </attributes>
    <attributes store="02">
      <allow_purchase>0</allow_purchase>
      <visibility>none</visibility>
    </attributes>
    <attributes store="66">
      <allow_purchase>0</allow_purchase>
      <visibility>none</visibility>
    </attributes>
    <links>
      <link type="relation"/>
    </links>
    <type>simple</type>
  </product>
  <product>
    <sku>VOE4784031</sku>
    <name>DISTANSRING</name>
    <status>enabled</status>
    <attributes store="admin">
      <status>1</status>
      <c4_status>8</c4_status>
      <m3_status>20</m3_status>
      <is_returnable>0</is_returnable>
      <allow_purchase>1</allow_purchase>
      <allow_guest_purchase>1</allow_guest_purchase>
      <allow_backorders>1</allow_backorders>
      <manufacturer></manufacturer>
      <c4_sysid>731141</c4_sysid>
      <updated_at>2021-01-18T10:53:38.584000</updated_at>
      <dangerous_goods>0</dangerous_goods>
      <competitor_references>&quot;&quot;</competitor_references>
      <supplier>001</supplier>
      <visibility>both</visibility>
    </attributes>
    <attributes store="01">
      <allow_purchase>0</allow_purchase>
      <allow_guest_purchase>0</allow_guest_purchase>
      <price>748.000000</price>
      <visibility>none</visibility>
    </attributes>
    <attributes store="02">
      <allow_purchase>0</allow_purchase>
      <visibility>none</visibility>
    </attributes>
    <attributes store="66">
      <allow_purchase>0</allow_purchase>
      <visibility>none</visibility>
    </attributes>
    <links>
      <link type="relation"/>
    </links>
    <type>simple</type>
  </product>
  <product>
    <sku>VOE4774637</sku>
    <name>OLJERÖR</name>
    <status>enabled</status>
    <attributes store="admin">
      <status>1</status>
      <c4_status>8</c4_status>
      <m3_status>20</m3_status>
      <is_returnable>0</is_returnable>
      <allow_purchase>1</allow_purchase>
      <allow_guest_purchase>1</allow_guest_purchase>
      <allow_backorders>1</allow_backorders>
      <manufacturer></manufacturer>
      <c4_sysid>733453</c4_sysid>
      <updated_at>2021-01-18T10:53:38.725000</updated_at>
      <dangerous_goods>0</dangerous_goods>
      <competitor_references>&quot;&quot;</competitor_references>
      <supplier>001</supplier>
      <visibility>both</visibility>
    </attributes>
    <attributes store="01">
      <allow_purchase>0</allow_purchase>
      <allow_guest_purchase>0</allow_guest_purchase>
      <price>1133.000000</price>
      <visibility>none</visibility>
    </attributes>
    <attributes store="02">
      <allow_purchase>0</allow_purchase>
      <visibility>none</visibility>
    </attributes>
    <attributes store="66">
      <allow_purchase>0</allow_purchase>
      <visibility>none</visibility>
    </attributes>
    <links>
      <link type="relation"/>
    </links>
    <type>simple</type>
  </product>
  <product>
    <sku>VOE20586427</sku>
    <name>VALVE</name>
    <status>enabled</status>
    <attributes store="admin">
      <status>1</status>
      <c4_status>8</c4_status>
      <m3_status>20</m3_status>
      <is_returnable>0</is_returnable>
      <allow_purchase>1</allow_purchase>
      <allow_guest_purchase>1</allow_guest_purchase>
      <allow_backorders>1</allow_backorders>
      <manufacturer></manufacturer>
      <c4_sysid>1786310</c4_sysid>
      <ean_number>7322236199710</ean_number>
      <updated_at>2021-01-18T10:53:38.850000</updated_at>
      <dangerous_goods>0</dangerous_goods>
      <competitor_references>&quot;&quot;</competitor_references>
      <supplier>001</supplier>
      <visibility>both</visibility>
    </attributes>
    <attributes store="01">
      <allow_purchase>0</allow_purchase>
      <allow_guest_purchase>0</allow_guest_purchase>
      <price>1441.000000</price>
      <visibility>none</visibility>
    </attributes>
    <attributes store="02">
      <allow_purchase>0</allow_purchase>
      <visibility>none</visibility>
    </attributes>
    <attributes store="66">
      <allow_purchase>0</allow_purchase>
      <visibility>none</visibility>
    </attributes>
    <links>
      <link type="relation"/>
    </links>
    <type>simple</type>
  </product>
  <product>
    <sku>VOE4871078</sku>
    <name>KUGGHJUL</name>
    <status>enabled</status>
    <attributes store="admin">
      <status>1</status>
      <c4_status>8</c4_status>
      <m3_status>20</m3_status>
      <is_returnable>0</is_returnable>
      <allow_purchase>1</allow_purchase>
      <allow_guest_purchase>1</allow_guest_purchase>
      <allow_backorders>1</allow_backorders>
      <manufacturer></manufacturer>
      <c4_sysid>734022</c4_sysid>
      <updated_at>2021-01-18T10:53:39.006000</updated_at>
      <dangerous_goods>0</dangerous_goods>
      <competitor_references>&quot;&quot;</competitor_references>
      <supplier>001</supplier>
      <visibility>both</visibility>
    </attributes>
    <attributes store="01">
      <allow_purchase>0</allow_purchase>
      <allow_guest_purchase>0</allow_guest_purchase>
      <price>13592.000000</price>
      <visibility>none</visibility>
    </attributes>
    <attributes store="02">
      <allow_purchase>0</allow_purchase>
      <visibility>none</visibility>
    </attributes>
    <attributes store="66">
      <allow_purchase>0</allow_purchase>
      <visibility>none</visibility>
    </attributes>
    <links>
      <link type="relation"/>
    </links>
    <type>simple</type>
  </product>
  <product>
    <sku>VOE15211723</sku>
    <name>VALVE</name>
    <status>enabled</status>
    <attributes store="admin">
      <status>1</status>
      <c4_status>8</c4_status>
      <m3_status>20</m3_status>
      <is_returnable>0</is_returnable>
      <allow_purchase>1</allow_purchase>
      <allow_guest_purchase>1</allow_guest_purchase>
      <allow_backorders>1</allow_backorders>
      <manufacturer></manufacturer>
      <c4_sysid>724546</c4_sysid>
      <ean_number>7322235872348</ean_number>
      <updated_at>2021-01-18T10:53:39.147000</updated_at>
      <dangerous_goods>0</dangerous_goods>
      <competitor_references>&quot;&quot;</competitor_references>
      <supplier>001</supplier>
      <visibility>both</visibility>
    </attributes>
    <attributes store="01">
      <allow_purchase>0</allow_purchase>
      <allow_guest_purchase>0</allow_guest_purchase>
      <price>11097.000000</price>
      <visibility>none</visibility>
    </attributes>
    <attributes store="02">
      <allow_purchase>0</allow_purchase>
      <visibility>none</visibility>
    </attributes>
    <attributes store="66">
      <allow_purchase>0</allow_purchase>
      <visibility>none</visibility>
    </attributes>
    <links>
      <link type="relation"/>
    </links>
    <type>simple</type>
  </product>
  <product>
    <sku>VOE4771375</sku>
    <name>DISTANSRING</name>
    <status>enabled</status>
    <attributes store="admin">
      <status>1</status>
      <c4_status>8</c4_status>
      <m3_status>20</m3_status>
      <is_returnable>0</is_returnable>
      <allow_purchase>1</allow_purchase>
      <allow_guest_purchase>1</allow_guest_purchase>
      <allow_backorders>1</allow_backorders>
      <manufacturer></manufacturer>
      <c4_sysid>735479</c4_sysid>
      <updated_at>2021-01-18T10:53:39.287000</updated_at>
      <dangerous_goods>0</dangerous_goods>
      <competitor_references>&quot;&quot;</competitor_references>
      <supplier>001</supplier>
      <visibility>both</visibility>
    </attributes>
    <attributes store="01">
      <allow_purchase>0</allow_purchase>
      <allow_guest_purchase>0</allow_guest_purchase>
      <price>743.000000</price>
      <visibility>none</visibility>
    </attributes>
    <attributes store="02">
      <allow_purchase>0</allow_purchase>
      <visibility>none</visibility>
    </attributes>
    <attributes store="66">
      <allow_purchase>0</allow_purchase>
      <visibility>none</visibility>
    </attributes>
    <links>
      <link type="relation"/>
    </links>
    <type>simple</type>
  </product>
  <product>
    <sku>VOE20459140</sku>
    <name>RAMLAGER</name>
    <status>enabled</status>
    <attributes store="admin">
      <status>1</status>
      <c4_status>8</c4_status>
      <m3_status>20</m3_status>
      <is_returnable>0</is_returnable>
      <allow_purchase>1</allow_purchase>
      <allow_guest_purchase>1</allow_guest_purchase>
      <allow_backorders>1</allow_backorders>
      <manufacturer></manufacturer>
      <c4_sysid>737470</c4_sysid>
      <ean_number>7322234133419</ean_number>
      <updated_at>2021-01-18T10:53:39.397000</updated_at>
      <dangerous_goods>0</dangerous_goods>
      <competitor_references>&quot;&quot;</competitor_references>
      <supplier>001</supplier>
      <visibility>both</visibility>
    </attributes>
    <attributes store="01">
      <allow_purchase>0</allow_purchase>
      <allow_guest_purchase>0</allow_guest_purchase>
      <price>262.000000</price>
      <visibility>none</visibility>
    </attributes>
    <attributes store="02">
      <allow_purchase>0</allow_purchase>
      <visibility>none</visibility>
    </attributes>
    <attributes store="66">
      <allow_purchase>0</allow_purchase>
      <visibility>none</visibility>
    </attributes>
    <links>
      <link type="relation"/>
    </links>
    <type>simple</type>
  </product>
  <product>
    <sku>VOE15637233</sku>
    <name>TRACK KIT</name>
    <status>enabled</status>
    <attributes store="admin">
      <status>1</status>
      <c4_status>8</c4_status>
      <m3_status>20</m3_status>
      <is_returnable>0</is_returnable>
      <allow_purchase>1</allow_purchase>
      <allow_guest_purchase>1</allow_guest_purchase>
      <allow_backorders>1</allow_backorders>
      <manufacturer></manufacturer>
      <c4_sysid>725979</c4_sysid>
      <replaces>&quot;VOE11802698&quot;</replaces>
      <updated_at>2021-01-18T10:53:39.506000</updated_at>
      <dangerous_goods>0</dangerous_goods>
      <competitor_references>&quot;&quot;</competitor_references>
      <supplier>001</supplier>
      <visibility>both</visibility>
    </attributes>
    <attributes store="01">
      <allow_purchase>0</allow_purchase>
      <allow_guest_purchase>0</allow_guest_purchase>
      <price>13776.000000</price>
      <visibility>none</visibility>
    </attributes>
    <attributes store="02">
      <allow_purchase>0</allow_purchase>
      <visibility>none</visibility>
    </attributes>
    <attributes store="66">
      <allow_purchase>0</allow_purchase>
      <visibility>none</visibility>
    </attributes>
    <links>
      <link type="relation"/>
    </links>
    <type>simple</type>
  </product>
  <product>
    <sku>VOE3152148</sku>
    <name>FINAL DRIVE</name>
    <status>enabled</status>
    <attributes store="admin">
      <status>1</status>
      <c4_status>8</c4_status>
      <m3_status>20</m3_status>
      <is_returnable>0</is_returnable>
      <allow_purchase>1</allow_purchase>
      <allow_guest_purchase>1</allow_guest_purchase>
      <allow_backorders>1</allow_backorders>
      <manufacturer></manufacturer>
      <c4_sysid>1198112</c4_sysid>
      <ean_number>7322236008685</ean_number>
      <updated_at>2021-01-18T10:53:39.647000</updated_at>
      <dangerous_goods>0</dangerous_goods>
      <competitor_references>&quot;&quot;</competitor_references>
      <supplier>001</supplier>
      <visibility>both</visibility>
    </attributes>
    <attributes store="01">
      <allow_purchase>0</allow_purchase>
      <allow_guest_purchase>0</allow_guest_purchase>
      <price>158547.000000</price>
      <visibility>none</visibility>
    </attributes>
    <attributes store="02">
      <allow_purchase>0</allow_purchase>
      <visibility>none</visibility>
    </attributes>
    <attributes store="66">
      <allow_purchase>0</allow_purchase>
      <visibility>none</visibility>
    </attributes>
    <links>
      <link type="relation"/>
    </links>
    <type>simple</type>
  </product>
  <product>
    <sku>VOE1522006</sku>
    <name>DISTANSRING</name>
    <status>enabled</status>
    <attributes store="admin">
      <status>1</status>
      <c4_status>8</c4_status>
      <m3_status>20</m3_status>
      <is_returnable>0</is_returnable>
      <allow_purchase>1</allow_purchase>
      <allow_guest_purchase>1</allow_guest_purchase>
      <allow_backorders>1</allow_backorders>
      <manufacturer></manufacturer>
      <c4_sysid>730334</c4_sysid>
      <updated_at>2021-01-18T10:53:39.756000</updated_at>
      <dangerous_goods>0</dangerous_goods>
      <competitor_references>&quot;&quot;</competitor_references>
      <supplier>001</supplier>
      <visibility>both</visibility>
    </attributes>
    <attributes store="01">
      <allow_purchase>0</allow_purchase>
      <allow_guest_purchase>0</allow_guest_purchase>
      <price>816.000000</price>
      <visibility>none</visibility>
    </attributes>
    <attributes store="02">
      <allow_purchase>0</allow_purchase>
      <visibility>none</visibility>
    </attributes>
    <attributes store="66">
      <allow_purchase>0</allow_purchase>
      <visibility>none</visibility>
    </attributes>
    <links>
      <link type="relation"/>
    </links>
    <type>simple</type>
  </product>
  <product>
    <sku>VOE15178154</sku>
    <name>CYLINDERHUVUDSA</name>
    <status>enabled</status>
    <attributes store="admin">
      <status>1</status>
      <c4_status>8</c4_status>
      <m3_status>20</m3_status>
      <is_returnable>0</is_returnable>
      <allow_purchase>1</allow_purchase>
      <allow_guest_purchase>1</allow_guest_purchase>
      <allow_backorders>1</allow_backorders>
      <manufacturer></manufacturer>
      <c4_sysid>728640</c4_sysid>
      <ean_number>7322235031059</ean_number>
      <updated_at>2021-01-18T10:53:39.897000</updated_at>
      <dangerous_goods>0</dangerous_goods>
      <competitor_references>&quot;&quot;</competitor_references>
      <supplier>001</supplier>
      <visibility>both</visibility>
    </attributes>
    <attributes store="01">
      <allow_purchase>0</allow_purchase>
      <allow_guest_purchase>0</allow_guest_purchase>
      <price>16918.000000</price>
      <visibility>none</visibility>
    </attributes>
    <attributes store="02">
      <allow_purchase>0</allow_purchase>
      <visibility>none</visibility>
    </attributes>
    <attributes store="66">
      <allow_purchase>0</allow_purchase>
      <visibility>none</visibility>
    </attributes>
    <links>
      <link type="relation"/>
    </links>
    <type>simple</type>
  </product>
  <product>
    <sku>VOE4782565</sku>
    <name>LÄNKLAGERTÄTN.</name>
    <status>enabled</status>
    <attributes store="admin">
      <status>1</status>
      <c4_status>8</c4_status>
      <m3_status>20</m3_status>
      <is_returnable>0</is_returnable>
      <allow_purchase>1</allow_purchase>
      <allow_guest_purchase>1</allow_guest_purchase>
      <allow_backorders>1</allow_backorders>
      <manufacturer></manufacturer>
      <c4_sysid>735191</c4_sysid>
      <updated_at>2021-01-18T10:53:40.022000</updated_at>
      <dangerous_goods>0</dangerous_goods>
      <competitor_references>&quot;&quot;</competitor_references>
      <supplier>001</supplier>
      <visibility>both</visibility>
    </attributes>
    <attributes store="01">
      <allow_purchase>0</allow_purchase>
      <allow_guest_purchase>0</allow_guest_purchase>
      <price>1110.000000</price>
      <visibility>none</visibility>
    </attributes>
    <attributes store="02">
      <allow_purchase>0</allow_purchase>
      <visibility>none</visibility>
    </attributes>
    <attributes store="66">
      <allow_purchase>0</allow_purchase>
      <visibility>none</visibility>
    </attributes>
    <links>
      <link type="relation"/>
    </links>
    <type>simple</type>
  </product>
  <product>
    <sku>VOE1661254</sku>
    <name>OLJEKYLARE</name>
    <status>enabled</status>
    <attributes store="admin">
      <status>1</status>
      <c4_status>8</c4_status>
      <m3_status>20</m3_status>
      <is_returnable>0</is_returnable>
      <allow_purchase>1</allow_purchase>
      <allow_guest_purchase>1</allow_guest_purchase>
      <allow_backorders>1</allow_backorders>
      <manufacturer></manufacturer>
      <c4_sysid>732497</c4_sysid>
      <updated_at>2021-01-18T10:53:40.131000</updated_at>
      <dangerous_goods>0</dangerous_goods>
      <competitor_references>&quot;&quot;</competitor_references>
      <supplier>001</supplier>
      <visibility>both</visibility>
    </attributes>
    <attributes store="01">
      <allow_purchase>0</allow_purchase>
      <allow_guest_purchase>0</allow_guest_purchase>
      <price>19021.000000</price>
      <visibility>none</visibility>
    </attributes>
    <attributes store="02">
      <allow_purchase>0</allow_purchase>
      <visibility>none</visibility>
    </attributes>
    <attributes store="66">
      <allow_purchase>0</allow_purchase>
      <visibility>none</visibility>
    </attributes>
    <links>
      <link type="relation"/>
    </links>
    <type>simple</type>
  </product>
  <product>
    <sku>VOE4094914</sku>
    <name>PLUGG</name>
    <status>enabled</status>
    <attributes store="admin">
      <status>1</status>
      <c4_status>8</c4_status>
      <m3_status>20</m3_status>
      <is_returnable>0</is_returnable>
      <allow_purchase>1</allow_purchase>
      <allow_guest_purchase>1</allow_guest_purchase>
      <allow_backorders>1</allow_backorders>
      <manufacturer></manufacturer>
      <c4_sysid>731266</c4_sysid>
      <updated_at>2021-01-18T10:53:40.256000</updated_at>
      <dangerous_goods>0</dangerous_goods>
      <competitor_references>&quot;&quot;</competitor_references>
      <supplier>001</supplier>
      <visibility>both</visibility>
    </attributes>
    <attributes store="01">
      <allow_purchase>0</allow_purchase>
      <allow_guest_purchase>0</allow_guest_purchase>
      <price>125.000000</price>
      <visibility>none</visibility>
    </attributes>
    <attributes store="02">
      <allow_purchase>0</allow_purchase>
      <visibility>none</visibility>
    </attributes>
    <attributes store="66">
      <allow_purchase>0</allow_purchase>
      <visibility>none</visibility>
    </attributes>
    <links>
      <link type="relation"/>
    </links>
    <type>simple</type>
  </product>
  <product>
    <sku>VOE16321491</sku>
    <name>SEAT BRACKET</name>
    <status>enabled</status>
    <attributes store="admin">
      <status>1</status>
      <c4_status>8</c4_status>
      <m3_status>20</m3_status>
      <is_returnable>0</is_returnable>
      <allow_purchase>1</allow_purchase>
      <allow_guest_purchase>1</allow_guest_purchase>
      <allow_backorders>1</allow_backorders>
      <manufacturer></manufacturer>
      <c4_sysid>1191149</c4_sysid>
      <replaces>&quot;VOE17473665&quot;</replaces>
      <updated_at>2021-01-18T10:53:40.381000</updated_at>
      <dangerous_goods>0</dangerous_goods>
      <competitor_references>&quot;&quot;</competitor_references>
      <supplier>001</supplier>
      <visibility>both</visibility>
    </attributes>
    <attributes store="01">
      <allow_purchase>0</allow_purchase>
      <allow_guest_purchase>0</allow_guest_purchase>
      <price>6160.000000</price>
      <visibility>none</visibility>
    </attributes>
    <attributes store="02">
      <allow_purchase>0</allow_purchase>
      <visibility>none</visibility>
    </attributes>
    <attributes store="66">
      <allow_purchase>0</allow_purchase>
      <visibility>none</visibility>
    </attributes>
    <links>
      <link type="relation"/>
    </links>
    <type>simple</type>
  </product>
  <product>
    <sku>VOE17409229</sku>
    <name>SLEEVE</name>
    <status>enabled</status>
    <attributes store="admin">
      <status>1</status>
      <c4_status>8</c4_status>
      <m3_status>20</m3_status>
      <is_returnable>0</is_returnable>
      <allow_purchase>1</allow_purchase>
      <allow_guest_purchase>1</allow_guest_purchase>
      <allow_backorders>1</allow_backorders>
      <manufacturer></manufacturer>
      <c4_sysid>732499</c4_sysid>
      <replaces>&quot;VOE11168049&quot;</replaces>
      <updated_at>2021-01-18T10:53:40.506000</updated_at>
      <categories>1326436,1326443</categories>
      <dangerous_goods>0</dangerous_goods>
      <competitor_references>&quot;&quot;</competitor_references>
      <supplier>001</supplier>
      <visibility>both</visibility>
    </attributes>
    <attributes store="01">
      <allow_purchase>0</allow_purchase>
      <allow_guest_purchase>0</allow_guest_purchase>
      <price>3514.000000</price>
      <visibility>none</visibility>
    </attributes>
    <attributes store="02">
      <allow_purchase>0</allow_purchase>
      <visibility>none</visibility>
    </attributes>
    <attributes store="66">
      <allow_purchase>0</allow_purchase>
      <visibility>none</visibility>
    </attributes>
    <links>
      <link type="relation"/>
    </links>
    <type>simple</type>
  </product>
  <product>
    <sku>VOE16897619</sku>
    <name>AIR INLET PIPE</name>
    <status>enabled</status>
    <attributes store="admin">
      <status>1</status>
      <c4_status>8</c4_status>
      <m3_status>20</m3_status>
      <is_returnable>0</is_returnable>
      <allow_purchase>1</allow_purchase>
      <allow_guest_purchase>1</allow_guest_purchase>
      <allow_backorders>1</allow_backorders>
      <manufacturer></manufacturer>
      <c4_sysid>1199637</c4_sysid>
      <ean_number>7322236119657</ean_number>
      <updated_at>2021-01-18T10:53:40.616000</updated_at>
      <dangerous_goods>0</dangerous_goods>
      <competitor_references>&quot;&quot;</competitor_references>
      <supplier>001</supplier>
      <visibility>both</visibility>
    </attributes>
    <attributes store="01">
      <allow_purchase>0</allow_purchase>
      <allow_guest_purchase>0</allow_guest_purchase>
      <price>3220.000000</price>
      <visibility>none</visibility>
    </attributes>
    <attributes store="02">
      <allow_purchase>0</allow_purchase>
      <visibility>none</visibility>
    </attributes>
    <attributes store="66">
      <allow_purchase>0</allow_purchase>
      <visibility>none</visibility>
    </attributes>
    <links>
      <link type="relation"/>
    </links>
    <type>simple</type>
  </product>
  <product>
    <sku>VOE20557401</sku>
    <name>BRACKET</name>
    <status>enabled</status>
    <attributes store="admin">
      <status>1</status>
      <c4_status>8</c4_status>
      <m3_status>20</m3_status>
      <is_returnable>0</is_returnable>
      <allow_purchase>1</allow_purchase>
      <allow_guest_purchase>1</allow_guest_purchase>
      <allow_backorders>1</allow_backorders>
      <manufacturer></manufacturer>
      <c4_sysid>1181345</c4_sysid>
      <ean_number>7322235875905</ean_number>
      <updated_at>2021-01-18T10:53:40.741000</updated_at>
      <dangerous_goods>0</dangerous_goods>
      <competitor_references>&quot;&quot;</competitor_references>
      <supplier>001</supplier>
      <visibility>both</visibility>
    </attributes>
    <attributes store="01">
      <allow_purchase>0</allow_purchase>
      <allow_guest_purchase>0</allow_guest_purchase>
      <price>2622.000000</price>
      <visibility>none</visibility>
    </attributes>
    <attributes store="02">
      <allow_purchase>0</allow_purchase>
      <visibility>none</visibility>
    </attributes>
    <attributes store="66">
      <allow_purchase>0</allow_purchase>
      <visibility>none</visibility>
    </attributes>
    <links>
      <link type="relation"/>
    </links>
    <type>simple</type>
  </product>
  <product>
    <sku>VOE4771446</sku>
    <name>VATTENPUMP</name>
    <status>enabled</status>
    <attributes store="admin">
      <status>1</status>
      <c4_status>8</c4_status>
      <m3_status>20</m3_status>
      <is_returnable>0</is_returnable>
      <allow_purchase>1</allow_purchase>
      <allow_guest_purchase>1</allow_guest_purchase>
      <allow_backorders>1</allow_backorders>
      <manufacturer></manufacturer>
      <c4_sysid>730596</c4_sysid>
      <updated_at>2021-01-18T10:53:41.038000</updated_at>
      <dangerous_goods>0</dangerous_goods>
      <competitor_references>&quot;&quot;</competitor_references>
      <supplier>001</supplier>
      <visibility>both</visibility>
    </attributes>
    <attributes store="01">
      <allow_purchase>0</allow_purchase>
      <allow_guest_purchase>0</allow_guest_purchase>
      <price>6646.000000</price>
      <visibility>none</visibility>
    </attributes>
    <attributes store="02">
      <allow_purchase>0</allow_purchase>
      <visibility>none</visibility>
    </attributes>
    <attributes store="66">
      <allow_purchase>0</allow_purchase>
      <visibility>none</visibility>
    </attributes>
    <links>
      <link type="relation"/>
    </links>
    <type>simple</type>
  </product>
</integrationbase>