<?xml version="1.0" encoding="utf-8"?>
<integrationbase>
  <product>
    <sku>VOE11400188</sku>
    <name>STÄNKSKÄRM</name>
    <status>enabled</status>
    <attributes store="admin">
      <status>1</status>
      <c4_status>8</c4_status>
      <m3_status>20</m3_status>
      <is_returnable>0</is_returnable>
      <allow_purchase>1</allow_purchase>
      <allow_guest_purchase>1</allow_guest_purchase>
      <allow_backorders>1</allow_backorders>
      <manufacturer></manufacturer>
      <c4_sysid>709856</c4_sysid>
      <updated_at>2021-01-18T09:21:27.506000</updated_at>
      <dangerous_goods>0</dangerous_goods>
      <competitor_references>&quot;&quot;</competitor_references>
      <supplier>001</supplier>
      <visibility>both</visibility>
    </attributes>
    <attributes store="01">
      <allow_purchase>0</allow_purchase>
      <allow_guest_purchase>0</allow_guest_purchase>
      <price>25959.000000</price>
      <visibility>none</visibility>
    </attributes>
    <attributes store="02">
      <allow_purchase>0</allow_purchase>
      <visibility>none</visibility>
    </attributes>
    <attributes store="66">
      <allow_purchase>0</allow_purchase>
      <visibility>none</visibility>
    </attributes>
    <links>
      <link type="relation"/>
    </links>
    <type>simple</type>
  </product>
  <product>
    <sku>VOE11370862</sku>
    <name>LÅSHYLSA</name>
    <status>enabled</status>
    <attributes store="admin">
      <status>1</status>
      <c4_status>8</c4_status>
      <m3_status>20</m3_status>
      <is_returnable>0</is_returnable>
      <allow_purchase>1</allow_purchase>
      <allow_guest_purchase>1</allow_guest_purchase>
      <allow_backorders>1</allow_backorders>
      <manufacturer></manufacturer>
      <c4_sysid>705660</c4_sysid>
      <updated_at>2021-01-18T09:21:27.756000</updated_at>
      <dangerous_goods>0</dangerous_goods>
      <competitor_references>&quot;&quot;</competitor_references>
      <supplier>001</supplier>
      <visibility>both</visibility>
    </attributes>
    <attributes store="01">
      <allow_purchase>0</allow_purchase>
      <allow_guest_purchase>0</allow_guest_purchase>
      <price>1416.000000</price>
      <visibility>none</visibility>
    </attributes>
    <attributes store="02">
      <allow_purchase>0</allow_purchase>
      <visibility>none</visibility>
    </attributes>
    <attributes store="66">
      <allow_purchase>0</allow_purchase>
      <visibility>none</visibility>
    </attributes>
    <links>
      <link type="relation"/>
    </links>
    <type>simple</type>
  </product>
  <product>
    <sku>VOE11075152</sku>
    <name>SPÄNNBAND</name>
    <status>enabled</status>
    <attributes store="admin">
      <status>1</status>
      <c4_status>8</c4_status>
      <m3_status>20</m3_status>
      <is_returnable>0</is_returnable>
      <allow_purchase>1</allow_purchase>
      <allow_guest_purchase>1</allow_guest_purchase>
      <allow_backorders>1</allow_backorders>
      <manufacturer></manufacturer>
      <c4_sysid>699196</c4_sysid>
      <updated_at>2021-01-18T09:21:27.881000</updated_at>
      <dangerous_goods>0</dangerous_goods>
      <competitor_references>&quot;&quot;</competitor_references>
      <supplier>001</supplier>
      <visibility>both</visibility>
    </attributes>
    <attributes store="01">
      <allow_purchase>0</allow_purchase>
      <allow_guest_purchase>0</allow_guest_purchase>
      <price>243.000000</price>
      <visibility>none</visibility>
    </attributes>
    <attributes store="02">
      <allow_purchase>0</allow_purchase>
      <visibility>none</visibility>
    </attributes>
    <attributes store="66">
      <allow_purchase>0</allow_purchase>
      <visibility>none</visibility>
    </attributes>
    <links>
      <link type="relation"/>
    </links>
    <type>simple</type>
  </product>
  <product>
    <sku>VOE11707884</sku>
    <name>ÖVERTYCKSVENTIL</name>
    <status>enabled</status>
    <attributes store="admin">
      <status>1</status>
      <c4_status>8</c4_status>
      <m3_status>20</m3_status>
      <is_returnable>0</is_returnable>
      <allow_purchase>1</allow_purchase>
      <allow_guest_purchase>1</allow_guest_purchase>
      <allow_backorders>1</allow_backorders>
      <manufacturer></manufacturer>
      <c4_sysid>706535</c4_sysid>
      <updated_at>2021-01-18T09:21:28.037000</updated_at>
      <dangerous_goods>0</dangerous_goods>
      <competitor_references>&quot;&quot;</competitor_references>
      <supplier>001</supplier>
      <visibility>both</visibility>
    </attributes>
    <attributes store="01">
      <allow_purchase>0</allow_purchase>
      <allow_guest_purchase>0</allow_guest_purchase>
      <price>9660.000000</price>
      <visibility>none</visibility>
    </attributes>
    <attributes store="02">
      <allow_purchase>0</allow_purchase>
      <visibility>none</visibility>
    </attributes>
    <attributes store="66">
      <allow_purchase>0</allow_purchase>
      <visibility>none</visibility>
    </attributes>
    <links>
      <link type="relation"/>
    </links>
    <type>simple</type>
  </product>
  <product>
    <sku>VOE11090893</sku>
    <name>T-RÖR</name>
    <status>enabled</status>
    <attributes store="admin">
      <status>1</status>
      <c4_status>8</c4_status>
      <m3_status>20</m3_status>
      <is_returnable>0</is_returnable>
      <allow_purchase>1</allow_purchase>
      <allow_guest_purchase>1</allow_guest_purchase>
      <allow_backorders>1</allow_backorders>
      <manufacturer></manufacturer>
      <c4_sysid>693611</c4_sysid>
      <updated_at>2021-01-18T09:21:28.193000</updated_at>
      <dangerous_goods>0</dangerous_goods>
      <competitor_references>&quot;&quot;</competitor_references>
      <supplier>001</supplier>
      <visibility>both</visibility>
    </attributes>
    <attributes store="01">
      <allow_purchase>0</allow_purchase>
      <allow_guest_purchase>0</allow_guest_purchase>
      <price>1363.000000</price>
      <visibility>none</visibility>
    </attributes>
    <attributes store="02">
      <allow_purchase>0</allow_purchase>
      <visibility>none</visibility>
    </attributes>
    <attributes store="66">
      <allow_purchase>0</allow_purchase>
      <visibility>none</visibility>
    </attributes>
    <links>
      <link type="relation"/>
    </links>
    <type>simple</type>
  </product>
  <product>
    <sku>VOE11101471</sku>
    <name>FÄSTE</name>
    <status>enabled</status>
    <attributes store="admin">
      <status>1</status>
      <c4_status>8</c4_status>
      <m3_status>20</m3_status>
      <is_returnable>0</is_returnable>
      <allow_purchase>1</allow_purchase>
      <allow_guest_purchase>1</allow_guest_purchase>
      <allow_backorders>1</allow_backorders>
      <manufacturer></manufacturer>
      <c4_sysid>695074</c4_sysid>
      <updated_at>2021-01-18T09:21:28.334000</updated_at>
      <dangerous_goods>0</dangerous_goods>
      <competitor_references>&quot;&quot;</competitor_references>
      <supplier>001</supplier>
      <visibility>both</visibility>
    </attributes>
    <attributes store="01">
      <allow_purchase>0</allow_purchase>
      <allow_guest_purchase>0</allow_guest_purchase>
      <price>748.000000</price>
      <visibility>none</visibility>
    </attributes>
    <attributes store="02">
      <allow_purchase>0</allow_purchase>
      <visibility>none</visibility>
    </attributes>
    <attributes store="66">
      <allow_purchase>0</allow_purchase>
      <visibility>none</visibility>
    </attributes>
    <links>
      <link type="relation"/>
    </links>
    <type>simple</type>
  </product>
  <product>
    <sku>VOE11033740</sku>
    <name>VÄRMEVÄXLARE</name>
    <status>enabled</status>
    <attributes store="admin">
      <status>1</status>
      <c4_status>8</c4_status>
      <m3_status>20</m3_status>
      <is_returnable>0</is_returnable>
      <allow_purchase>1</allow_purchase>
      <allow_guest_purchase>1</allow_guest_purchase>
      <allow_backorders>1</allow_backorders>
      <manufacturer></manufacturer>
      <c4_sysid>699825</c4_sysid>
      <updated_at>2021-01-18T09:21:28.490000</updated_at>
      <dangerous_goods>0</dangerous_goods>
      <competitor_references>&quot;&quot;</competitor_references>
      <supplier>001</supplier>
      <visibility>both</visibility>
    </attributes>
    <attributes store="01">
      <allow_purchase>0</allow_purchase>
      <allow_guest_purchase>0</allow_guest_purchase>
      <price>14594.000000</price>
      <visibility>none</visibility>
    </attributes>
    <attributes store="02">
      <allow_purchase>0</allow_purchase>
      <visibility>none</visibility>
    </attributes>
    <attributes store="66">
      <allow_purchase>0</allow_purchase>
      <visibility>none</visibility>
    </attributes>
    <links>
      <link type="relation"/>
    </links>
    <type>simple</type>
  </product>
  <product>
    <sku>VOE11035675</sku>
    <name>DISTANSRING</name>
    <status>enabled</status>
    <attributes store="admin">
      <status>1</status>
      <c4_status>8</c4_status>
      <m3_status>20</m3_status>
      <is_returnable>0</is_returnable>
      <allow_purchase>1</allow_purchase>
      <allow_guest_purchase>1</allow_guest_purchase>
      <allow_backorders>1</allow_backorders>
      <manufacturer></manufacturer>
      <c4_sysid>693242</c4_sysid>
      <updated_at>2021-01-18T09:21:28.646000</updated_at>
      <dangerous_goods>0</dangerous_goods>
      <competitor_references>&quot;&quot;</competitor_references>
      <supplier>001</supplier>
      <visibility>both</visibility>
    </attributes>
    <attributes store="01">
      <allow_purchase>0</allow_purchase>
      <allow_guest_purchase>0</allow_guest_purchase>
      <price>376.000000</price>
      <visibility>none</visibility>
    </attributes>
    <attributes store="02">
      <allow_purchase>0</allow_purchase>
      <visibility>none</visibility>
    </attributes>
    <attributes store="66">
      <allow_purchase>0</allow_purchase>
      <visibility>none</visibility>
    </attributes>
    <links>
      <link type="relation"/>
    </links>
    <type>simple</type>
  </product>
  <product>
    <sku>VOE11705861</sku>
    <name>LÅSPLÅT</name>
    <status>enabled</status>
    <attributes store="admin">
      <status>1</status>
      <c4_status>8</c4_status>
      <m3_status>20</m3_status>
      <is_returnable>0</is_returnable>
      <allow_purchase>1</allow_purchase>
      <allow_guest_purchase>1</allow_guest_purchase>
      <allow_backorders>1</allow_backorders>
      <manufacturer></manufacturer>
      <c4_sysid>710568</c4_sysid>
      <replaces>&quot;ZM 2906428&quot;</replaces>
      <updated_at>2021-01-18T09:21:28.803000</updated_at>
      <dangerous_goods>0</dangerous_goods>
      <competitor_references>&quot;&quot;</competitor_references>
      <supplier>001</supplier>
      <visibility>both</visibility>
    </attributes>
    <attributes store="01">
      <allow_purchase>0</allow_purchase>
      <allow_guest_purchase>0</allow_guest_purchase>
      <price>63.000000</price>
      <visibility>none</visibility>
    </attributes>
    <attributes store="02">
      <allow_purchase>0</allow_purchase>
      <visibility>none</visibility>
    </attributes>
    <attributes store="66">
      <allow_purchase>0</allow_purchase>
      <visibility>none</visibility>
    </attributes>
    <links>
      <link type="relation"/>
    </links>
    <type>simple</type>
  </product>
  <product>
    <sku>VOE11307224</sku>
    <name>SLANG</name>
    <status>enabled</status>
    <attributes store="admin">
      <status>1</status>
      <c4_status>8</c4_status>
      <m3_status>20</m3_status>
      <is_returnable>0</is_returnable>
      <allow_purchase>1</allow_purchase>
      <allow_guest_purchase>1</allow_guest_purchase>
      <allow_backorders>1</allow_backorders>
      <manufacturer></manufacturer>
      <c4_sysid>706861</c4_sysid>
      <updated_at>2021-01-18T09:21:29.021000</updated_at>
      <dangerous_goods>0</dangerous_goods>
      <competitor_references>&quot;&quot;</competitor_references>
      <supplier>001</supplier>
      <visibility>both</visibility>
    </attributes>
    <attributes store="01">
      <allow_purchase>0</allow_purchase>
      <allow_guest_purchase>0</allow_guest_purchase>
      <price>2373.000000</price>
      <visibility>none</visibility>
    </attributes>
    <attributes store="02">
      <allow_purchase>0</allow_purchase>
      <visibility>none</visibility>
    </attributes>
    <attributes store="66">
      <allow_purchase>0</allow_purchase>
      <visibility>none</visibility>
    </attributes>
    <links>
      <link type="relation"/>
    </links>
    <type>simple</type>
  </product>
  <product>
    <sku>VOE11038368</sku>
    <name>LOCK</name>
    <status>enabled</status>
    <attributes store="admin">
      <status>1</status>
      <c4_status>8</c4_status>
      <m3_status>20</m3_status>
      <is_returnable>0</is_returnable>
      <allow_purchase>1</allow_purchase>
      <allow_guest_purchase>1</allow_guest_purchase>
      <allow_backorders>1</allow_backorders>
      <manufacturer></manufacturer>
      <c4_sysid>697529</c4_sysid>
      <updated_at>2021-01-18T09:21:29.131000</updated_at>
      <dangerous_goods>0</dangerous_goods>
      <competitor_references>&quot;&quot;</competitor_references>
      <supplier>001</supplier>
      <visibility>both</visibility>
    </attributes>
    <attributes store="01">
      <allow_purchase>0</allow_purchase>
      <allow_guest_purchase>0</allow_guest_purchase>
      <price>2554.000000</price>
      <visibility>none</visibility>
    </attributes>
    <attributes store="02">
      <allow_purchase>0</allow_purchase>
      <visibility>none</visibility>
    </attributes>
    <attributes store="66">
      <allow_purchase>0</allow_purchase>
      <visibility>none</visibility>
    </attributes>
    <links>
      <link type="relation"/>
    </links>
    <type>simple</type>
  </product>
  <product>
    <sku>VOE11705270</sku>
    <name>DRIVAXEL</name>
    <status>enabled</status>
    <attributes store="admin">
      <status>1</status>
      <c4_status>8</c4_status>
      <m3_status>20</m3_status>
      <is_returnable>0</is_returnable>
      <allow_purchase>1</allow_purchase>
      <allow_guest_purchase>1</allow_guest_purchase>
      <allow_backorders>1</allow_backorders>
      <manufacturer></manufacturer>
      <c4_sysid>712281</c4_sysid>
      <updated_at>2021-01-18T09:21:29.303000</updated_at>
      <dangerous_goods>0</dangerous_goods>
      <competitor_references>&quot;&quot;</competitor_references>
      <supplier>001</supplier>
      <visibility>both</visibility>
    </attributes>
    <attributes store="01">
      <allow_purchase>0</allow_purchase>
      <allow_guest_purchase>0</allow_guest_purchase>
      <price>5581.000000</price>
      <visibility>none</visibility>
    </attributes>
    <attributes store="02">
      <allow_purchase>0</allow_purchase>
      <visibility>none</visibility>
    </attributes>
    <attributes store="66">
      <allow_purchase>0</allow_purchase>
      <visibility>none</visibility>
    </attributes>
    <links>
      <link type="relation"/>
    </links>
    <type>simple</type>
  </product>
  <product>
    <sku>VOE11110762</sku>
    <name>CHARGE AIR COOL</name>
    <status>enabled</status>
    <attributes store="admin">
      <status>1</status>
      <c4_status>8</c4_status>
      <m3_status>20</m3_status>
      <is_returnable>0</is_returnable>
      <allow_purchase>1</allow_purchase>
      <allow_guest_purchase>1</allow_guest_purchase>
      <allow_backorders>1</allow_backorders>
      <manufacturer></manufacturer>
      <c4_sysid>701233</c4_sysid>
      <ean_number>7322235667500</ean_number>
      <updated_at>2021-01-18T09:21:29.475000</updated_at>
      <dangerous_goods>0</dangerous_goods>
      <competitor_references>&quot;&quot;</competitor_references>
      <supplier>001</supplier>
      <visibility>both</visibility>
    </attributes>
    <attributes store="01">
      <allow_purchase>0</allow_purchase>
      <allow_guest_purchase>0</allow_guest_purchase>
      <price>53601.000000</price>
      <visibility>none</visibility>
    </attributes>
    <attributes store="02">
      <allow_purchase>0</allow_purchase>
      <visibility>none</visibility>
    </attributes>
    <attributes store="66">
      <allow_purchase>0</allow_purchase>
      <visibility>none</visibility>
    </attributes>
    <links>
      <link type="relation"/>
    </links>
    <type>simple</type>
  </product>
  <product>
    <sku>VOE11081064</sku>
    <name>SPARSKÄR</name>
    <status>enabled</status>
    <attributes store="admin">
      <status>1</status>
      <c4_status>8</c4_status>
      <m3_status>20</m3_status>
      <is_returnable>0</is_returnable>
      <allow_purchase>1</allow_purchase>
      <allow_guest_purchase>1</allow_guest_purchase>
      <allow_backorders>1</allow_backorders>
      <manufacturer></manufacturer>
      <c4_sysid>694423</c4_sysid>
      <updated_at>2021-01-18T09:21:29.646000</updated_at>
      <dangerous_goods>0</dangerous_goods>
      <competitor_references>&quot;&quot;</competitor_references>
      <supplier>001</supplier>
      <visibility>both</visibility>
    </attributes>
    <attributes store="01">
      <allow_purchase>0</allow_purchase>
      <allow_guest_purchase>0</allow_guest_purchase>
      <price>5936.000000</price>
      <visibility>none</visibility>
    </attributes>
    <attributes store="02">
      <allow_purchase>0</allow_purchase>
      <visibility>none</visibility>
    </attributes>
    <attributes store="66">
      <allow_purchase>0</allow_purchase>
      <visibility>none</visibility>
    </attributes>
    <links>
      <link type="relation"/>
    </links>
    <type>simple</type>
  </product>
  <product>
    <sku>VOE11306273</sku>
    <name>HOSE ASSEMBLY</name>
    <status>enabled</status>
    <attributes store="admin">
      <status>1</status>
      <c4_status>8</c4_status>
      <m3_status>20</m3_status>
      <is_returnable>0</is_returnable>
      <allow_purchase>1</allow_purchase>
      <allow_guest_purchase>1</allow_guest_purchase>
      <allow_backorders>1</allow_backorders>
      <manufacturer></manufacturer>
      <c4_sysid>703841</c4_sysid>
      <updated_at>2021-01-18T09:21:29.787000</updated_at>
      <categories>1326710</categories>
      <dangerous_goods>0</dangerous_goods>
      <competitor_references>&quot;&quot;</competitor_references>
      <supplier>001</supplier>
      <visibility>both</visibility>
    </attributes>
    <attributes store="01">
      <allow_purchase>0</allow_purchase>
      <allow_guest_purchase>0</allow_guest_purchase>
      <price>1856.000000</price>
      <visibility>none</visibility>
    </attributes>
    <attributes store="02">
      <allow_purchase>0</allow_purchase>
      <visibility>none</visibility>
    </attributes>
    <attributes store="66">
      <allow_purchase>0</allow_purchase>
      <visibility>none</visibility>
    </attributes>
    <links>
      <link type="relation"/>
    </links>
    <type>simple</type>
  </product>
  <product>
    <sku>VOE11093390</sku>
    <name>FÄSTPLÅT</name>
    <status>enabled</status>
    <attributes store="admin">
      <status>1</status>
      <c4_status>8</c4_status>
      <m3_status>20</m3_status>
      <is_returnable>0</is_returnable>
      <allow_purchase>1</allow_purchase>
      <allow_guest_purchase>1</allow_guest_purchase>
      <allow_backorders>1</allow_backorders>
      <manufacturer></manufacturer>
      <c4_sysid>696955</c4_sysid>
      <updated_at>2021-01-18T09:21:29.959000</updated_at>
      <dangerous_goods>0</dangerous_goods>
      <competitor_references>&quot;&quot;</competitor_references>
      <supplier>001</supplier>
      <visibility>both</visibility>
    </attributes>
    <attributes store="01">
      <allow_purchase>0</allow_purchase>
      <allow_guest_purchase>0</allow_guest_purchase>
      <price>250.000000</price>
      <visibility>none</visibility>
    </attributes>
    <attributes store="02">
      <allow_purchase>0</allow_purchase>
      <visibility>none</visibility>
    </attributes>
    <attributes store="66">
      <allow_purchase>0</allow_purchase>
      <visibility>none</visibility>
    </attributes>
    <links>
      <link type="relation"/>
    </links>
    <type>simple</type>
  </product>
  <product>
    <sku>VOE11110284</sku>
    <name>LUFTFILTER</name>
    <status>enabled</status>
    <attributes store="admin">
      <status>1</status>
      <c4_status>8</c4_status>
      <m3_status>20</m3_status>
      <is_returnable>0</is_returnable>
      <allow_purchase>1</allow_purchase>
      <allow_guest_purchase>1</allow_guest_purchase>
      <allow_backorders>1</allow_backorders>
      <manufacturer></manufacturer>
      <c4_sysid>698775</c4_sysid>
      <updated_at>2021-01-18T09:21:30.115000</updated_at>
      <categories>1751764</categories>
      <dangerous_goods>0</dangerous_goods>
      <competitor_references>&quot;&quot;</competitor_references>
      <supplier>001</supplier>
      <visibility>both</visibility>
    </attributes>
    <attributes store="01">
      <allow_purchase>0</allow_purchase>
      <allow_guest_purchase>0</allow_guest_purchase>
      <price>446.000000</price>
      <visibility>none</visibility>
    </attributes>
    <attributes store="02">
      <allow_purchase>0</allow_purchase>
      <visibility>none</visibility>
    </attributes>
    <attributes store="66">
      <allow_purchase>0</allow_purchase>
      <visibility>none</visibility>
    </attributes>
    <links>
      <link type="relation"/>
    </links>
    <type>simple</type>
  </product>
  <product>
    <sku>VOE11702860</sku>
    <name>PLUGG</name>
    <status>enabled</status>
    <attributes store="admin">
      <status>1</status>
      <c4_status>8</c4_status>
      <m3_status>20</m3_status>
      <is_returnable>0</is_returnable>
      <allow_purchase>1</allow_purchase>
      <allow_guest_purchase>1</allow_guest_purchase>
      <allow_backorders>1</allow_backorders>
      <manufacturer></manufacturer>
      <c4_sysid>706922</c4_sysid>
      <updated_at>2021-01-18T09:21:30.256000</updated_at>
      <dangerous_goods>0</dangerous_goods>
      <competitor_references>&quot;&quot;</competitor_references>
      <supplier>001</supplier>
      <visibility>both</visibility>
    </attributes>
    <attributes store="01">
      <allow_purchase>0</allow_purchase>
      <allow_guest_purchase>0</allow_guest_purchase>
      <price>450.000000</price>
      <visibility>none</visibility>
    </attributes>
    <attributes store="02">
      <allow_purchase>0</allow_purchase>
      <visibility>none</visibility>
    </attributes>
    <attributes store="66">
      <allow_purchase>0</allow_purchase>
      <visibility>none</visibility>
    </attributes>
    <links>
      <link type="relation"/>
    </links>
    <type>simple</type>
  </product>
  <product>
    <sku>VOE11412655</sku>
    <name>COVER</name>
    <status>enabled</status>
    <attributes store="admin">
      <status>1</status>
      <c4_status>8</c4_status>
      <m3_status>20</m3_status>
      <is_returnable>0</is_returnable>
      <allow_purchase>1</allow_purchase>
      <allow_guest_purchase>1</allow_guest_purchase>
      <allow_backorders>1</allow_backorders>
      <manufacturer></manufacturer>
      <c4_sysid>706554</c4_sysid>
      <ean_number>7322235085120</ean_number>
      <updated_at>2021-01-18T09:21:30.412000</updated_at>
      <dangerous_goods>0</dangerous_goods>
      <competitor_references>&quot;&quot;</competitor_references>
      <supplier>001</supplier>
      <visibility>both</visibility>
    </attributes>
    <attributes store="01">
      <allow_purchase>0</allow_purchase>
      <allow_guest_purchase>0</allow_guest_purchase>
      <price>2241.000000</price>
      <visibility>none</visibility>
    </attributes>
    <attributes store="02">
      <allow_purchase>0</allow_purchase>
      <visibility>none</visibility>
    </attributes>
    <attributes store="66">
      <allow_purchase>0</allow_purchase>
      <visibility>none</visibility>
    </attributes>
    <links>
      <link type="relation"/>
    </links>
    <type>simple</type>
  </product>
  <product>
    <sku>VOE11027180</sku>
    <name>KYLARSLANG</name>
    <status>enabled</status>
    <attributes store="admin">
      <status>1</status>
      <c4_status>8</c4_status>
      <m3_status>20</m3_status>
      <is_returnable>0</is_returnable>
      <allow_purchase>1</allow_purchase>
      <allow_guest_purchase>1</allow_guest_purchase>
      <allow_backorders>1</allow_backorders>
      <manufacturer></manufacturer>
      <c4_sysid>699978</c4_sysid>
      <updated_at>2021-01-18T09:21:30.568000</updated_at>
      <dangerous_goods>0</dangerous_goods>
      <competitor_references>&quot;&quot;</competitor_references>
      <supplier>001</supplier>
      <visibility>both</visibility>
    </attributes>
    <attributes store="01">
      <allow_purchase>0</allow_purchase>
      <allow_guest_purchase>0</allow_guest_purchase>
      <price>1399.000000</price>
      <visibility>none</visibility>
    </attributes>
    <attributes store="02">
      <allow_purchase>0</allow_purchase>
      <visibility>none</visibility>
    </attributes>
    <attributes store="66">
      <allow_purchase>0</allow_purchase>
      <visibility>none</visibility>
    </attributes>
    <links>
      <link type="relation"/>
    </links>
    <type>simple</type>
  </product>
  <product>
    <sku>VOE11103004</sku>
    <name>RÖR</name>
    <status>enabled</status>
    <attributes store="admin">
      <status>1</status>
      <c4_status>8</c4_status>
      <m3_status>20</m3_status>
      <is_returnable>0</is_returnable>
      <allow_purchase>1</allow_purchase>
      <allow_guest_purchase>1</allow_guest_purchase>
      <allow_backorders>1</allow_backorders>
      <manufacturer></manufacturer>
      <c4_sysid>694740</c4_sysid>
      <updated_at>2021-01-18T09:21:30.740000</updated_at>
      <dangerous_goods>0</dangerous_goods>
      <competitor_references>&quot;&quot;</competitor_references>
      <supplier>001</supplier>
      <visibility>both</visibility>
    </attributes>
    <attributes store="01">
      <allow_purchase>0</allow_purchase>
      <allow_guest_purchase>0</allow_guest_purchase>
      <price>275.000000</price>
      <visibility>none</visibility>
    </attributes>
    <attributes store="02">
      <allow_purchase>0</allow_purchase>
      <visibility>none</visibility>
    </attributes>
    <attributes store="66">
      <allow_purchase>0</allow_purchase>
      <visibility>none</visibility>
    </attributes>
    <links>
      <link type="relation"/>
    </links>
    <type>simple</type>
  </product>
  <product>
    <sku>VOE11410836</sku>
    <name>ATTACHMENT</name>
    <status>enabled</status>
    <attributes store="admin">
      <status>1</status>
      <c4_status>8</c4_status>
      <m3_status>20</m3_status>
      <is_returnable>0</is_returnable>
      <allow_purchase>1</allow_purchase>
      <allow_guest_purchase>1</allow_guest_purchase>
      <allow_backorders>1</allow_backorders>
      <manufacturer></manufacturer>
      <c4_sysid>1171142</c4_sysid>
      <ean_number>7322235981248</ean_number>
      <updated_at>2021-01-18T09:21:31.068000</updated_at>
      <dangerous_goods>0</dangerous_goods>
      <competitor_references>&quot;&quot;</competitor_references>
      <supplier>001</supplier>
      <visibility>both</visibility>
    </attributes>
    <attributes store="01">
      <allow_purchase>0</allow_purchase>
      <allow_guest_purchase>0</allow_guest_purchase>
      <price>3182.000000</price>
      <visibility>none</visibility>
    </attributes>
    <attributes store="02">
      <allow_purchase>0</allow_purchase>
      <visibility>none</visibility>
    </attributes>
    <attributes store="66">
      <allow_purchase>0</allow_purchase>
      <visibility>none</visibility>
    </attributes>
    <links>
      <link type="relation"/>
    </links>
    <type>simple</type>
  </product>
  <product>
    <sku>VOE11117626</sku>
    <name>BRICKA</name>
    <status>enabled</status>
    <attributes store="admin">
      <status>1</status>
      <c4_status>8</c4_status>
      <m3_status>20</m3_status>
      <is_returnable>0</is_returnable>
      <allow_purchase>1</allow_purchase>
      <allow_guest_purchase>1</allow_guest_purchase>
      <allow_backorders>1</allow_backorders>
      <manufacturer></manufacturer>
      <c4_sysid>696053</c4_sysid>
      <ean_number>7322234317796</ean_number>
      <updated_at>2021-01-18T09:21:31.240000</updated_at>
      <dangerous_goods>0</dangerous_goods>
      <competitor_references>&quot;&quot;</competitor_references>
      <supplier>001</supplier>
      <visibility>both</visibility>
    </attributes>
    <attributes store="01">
      <allow_purchase>0</allow_purchase>
      <allow_guest_purchase>0</allow_guest_purchase>
      <price>712.000000</price>
      <visibility>none</visibility>
    </attributes>
    <attributes store="02">
      <allow_purchase>0</allow_purchase>
      <visibility>none</visibility>
    </attributes>
    <attributes store="66">
      <allow_purchase>0</allow_purchase>
      <visibility>none</visibility>
    </attributes>
    <links>
      <link type="relation"/>
    </links>
    <type>simple</type>
  </product>
  <product>
    <sku>VOE11185500</sku>
    <name>PAR</name>
    <status>enabled</status>
    <attributes store="admin">
      <status>1</status>
      <c4_status>8</c4_status>
      <m3_status>20</m3_status>
      <is_returnable>0</is_returnable>
      <allow_purchase>1</allow_purchase>
      <allow_guest_purchase>1</allow_guest_purchase>
      <allow_backorders>1</allow_backorders>
      <manufacturer></manufacturer>
      <c4_sysid>708924</c4_sysid>
      <updated_at>2021-01-18T09:21:31.428000</updated_at>
      <dangerous_goods>0</dangerous_goods>
      <competitor_references>&quot;&quot;</competitor_references>
      <supplier>001</supplier>
      <visibility>both</visibility>
    </attributes>
    <attributes store="01">
      <allow_purchase>0</allow_purchase>
      <allow_guest_purchase>0</allow_guest_purchase>
      <price>5081.000000</price>
      <visibility>none</visibility>
    </attributes>
    <attributes store="02">
      <allow_purchase>0</allow_purchase>
      <visibility>none</visibility>
    </attributes>
    <attributes store="66">
      <allow_purchase>0</allow_purchase>
      <visibility>none</visibility>
    </attributes>
    <links>
      <link type="relation"/>
    </links>
    <type>simple</type>
  </product>
  <product>
    <sku>VOE11704847</sku>
    <name>ÖVERTRYCKSVENT.</name>
    <status>enabled</status>
    <attributes store="admin">
      <status>1</status>
      <c4_status>8</c4_status>
      <m3_status>20</m3_status>
      <is_returnable>0</is_returnable>
      <allow_purchase>1</allow_purchase>
      <allow_guest_purchase>1</allow_guest_purchase>
      <allow_backorders>1</allow_backorders>
      <manufacturer></manufacturer>
      <c4_sysid>703067</c4_sysid>
      <updated_at>2021-01-18T09:21:31.584000</updated_at>
      <dangerous_goods>0</dangerous_goods>
      <competitor_references>&quot;&quot;</competitor_references>
      <supplier>001</supplier>
      <visibility>both</visibility>
    </attributes>
    <attributes store="01">
      <allow_purchase>0</allow_purchase>
      <allow_guest_purchase>0</allow_guest_purchase>
      <price>8692.000000</price>
      <visibility>none</visibility>
    </attributes>
    <attributes store="02">
      <allow_purchase>0</allow_purchase>
      <visibility>none</visibility>
    </attributes>
    <attributes store="66">
      <allow_purchase>0</allow_purchase>
      <visibility>none</visibility>
    </attributes>
    <links>
      <link type="relation"/>
    </links>
    <type>simple</type>
  </product>
  <product>
    <sku>VOE11050975</sku>
    <name>LOCK</name>
    <status>enabled</status>
    <attributes store="admin">
      <status>1</status>
      <c4_status>8</c4_status>
      <m3_status>20</m3_status>
      <is_returnable>0</is_returnable>
      <allow_purchase>1</allow_purchase>
      <allow_guest_purchase>1</allow_guest_purchase>
      <allow_backorders>1</allow_backorders>
      <manufacturer></manufacturer>
      <c4_sysid>699416</c4_sysid>
      <updated_at>2021-01-18T09:21:31.756000</updated_at>
      <dangerous_goods>0</dangerous_goods>
      <competitor_references>&quot;&quot;</competitor_references>
      <supplier>001</supplier>
      <visibility>both</visibility>
    </attributes>
    <attributes store="01">
      <allow_purchase>0</allow_purchase>
      <allow_guest_purchase>0</allow_guest_purchase>
      <price>6188.000000</price>
      <visibility>none</visibility>
    </attributes>
    <attributes store="02">
      <allow_purchase>0</allow_purchase>
      <visibility>none</visibility>
    </attributes>
    <attributes store="66">
      <allow_purchase>0</allow_purchase>
      <visibility>none</visibility>
    </attributes>
    <links>
      <link type="relation"/>
    </links>
    <type>simple</type>
  </product>
  <product>
    <sku>VOE11059565</sku>
    <name>TÄTNING</name>
    <status>enabled</status>
    <attributes store="admin">
      <status>1</status>
      <c4_status>8</c4_status>
      <m3_status>20</m3_status>
      <is_returnable>0</is_returnable>
      <allow_purchase>1</allow_purchase>
      <allow_guest_purchase>1</allow_guest_purchase>
      <allow_backorders>1</allow_backorders>
      <manufacturer></manufacturer>
      <c4_sysid>698974</c4_sysid>
      <ean_number>7322234904965</ean_number>
      <updated_at>2021-01-18T09:21:31.928000</updated_at>
      <dangerous_goods>0</dangerous_goods>
      <competitor_references>&quot;&quot;</competitor_references>
      <supplier>001</supplier>
      <visibility>both</visibility>
    </attributes>
    <attributes store="01">
      <allow_purchase>0</allow_purchase>
      <allow_guest_purchase>0</allow_guest_purchase>
      <price>134.000000</price>
      <visibility>none</visibility>
    </attributes>
    <attributes store="02">
      <allow_purchase>0</allow_purchase>
      <visibility>none</visibility>
    </attributes>
    <attributes store="66">
      <allow_purchase>0</allow_purchase>
      <visibility>none</visibility>
    </attributes>
    <links>
      <link type="relation"/>
    </links>
    <type>simple</type>
  </product>
  <product>
    <sku>VOE11400530</sku>
    <name>SIDOSTYCKE</name>
    <status>enabled</status>
    <attributes store="admin">
      <status>1</status>
      <c4_status>8</c4_status>
      <m3_status>20</m3_status>
      <is_returnable>0</is_returnable>
      <allow_purchase>1</allow_purchase>
      <allow_guest_purchase>1</allow_guest_purchase>
      <allow_backorders>1</allow_backorders>
      <manufacturer></manufacturer>
      <c4_sysid>705355</c4_sysid>
      <updated_at>2021-01-18T09:21:32.131000</updated_at>
      <dangerous_goods>0</dangerous_goods>
      <competitor_references>&quot;&quot;</competitor_references>
      <supplier>001</supplier>
      <visibility>both</visibility>
    </attributes>
    <attributes store="01">
      <allow_purchase>0</allow_purchase>
      <allow_guest_purchase>0</allow_guest_purchase>
      <price>52162.000000</price>
      <visibility>none</visibility>
    </attributes>
    <attributes store="02">
      <allow_purchase>0</allow_purchase>
      <visibility>none</visibility>
    </attributes>
    <attributes store="66">
      <allow_purchase>0</allow_purchase>
      <visibility>none</visibility>
    </attributes>
    <links>
      <link type="relation"/>
    </links>
    <type>simple</type>
  </product>
  <product>
    <sku>VOE11411400</sku>
    <name>CLAMP</name>
    <status>enabled</status>
    <attributes store="admin">
      <status>1</status>
      <c4_status>8</c4_status>
      <m3_status>20</m3_status>
      <is_returnable>0</is_returnable>
      <allow_purchase>1</allow_purchase>
      <allow_guest_purchase>1</allow_guest_purchase>
      <allow_backorders>1</allow_backorders>
      <manufacturer></manufacturer>
      <c4_sysid>707547</c4_sysid>
      <replaces>&quot;VOE4787936&quot;</replaces>
      <updated_at>2021-01-18T09:21:32.272000</updated_at>
      <dangerous_goods>0</dangerous_goods>
      <competitor_references>&quot;&quot;</competitor_references>
      <supplier>001</supplier>
      <visibility>both</visibility>
    </attributes>
    <attributes store="01">
      <allow_purchase>0</allow_purchase>
      <allow_guest_purchase>0</allow_guest_purchase>
      <price>255.000000</price>
      <visibility>none</visibility>
    </attributes>
    <attributes store="02">
      <allow_purchase>0</allow_purchase>
      <visibility>none</visibility>
    </attributes>
    <attributes store="66">
      <allow_purchase>0</allow_purchase>
      <visibility>none</visibility>
    </attributes>
    <links>
      <link type="relation"/>
    </links>
    <type>simple</type>
  </product>
  <product>
    <sku>VOE11101399</sku>
    <name>MOTVIKT</name>
    <status>enabled</status>
    <attributes store="admin">
      <status>1</status>
      <c4_status>8</c4_status>
      <m3_status>20</m3_status>
      <is_returnable>0</is_returnable>
      <allow_purchase>1</allow_purchase>
      <allow_guest_purchase>1</allow_guest_purchase>
      <allow_backorders>1</allow_backorders>
      <manufacturer></manufacturer>
      <c4_sysid>696526</c4_sysid>
      <updated_at>2021-01-18T09:21:32.428000</updated_at>
      <dangerous_goods>0</dangerous_goods>
      <competitor_references>&quot;&quot;</competitor_references>
      <supplier>001</supplier>
      <visibility>both</visibility>
    </attributes>
    <attributes store="01">
      <allow_purchase>0</allow_purchase>
      <allow_guest_purchase>0</allow_guest_purchase>
      <price>55705.000000</price>
      <visibility>none</visibility>
    </attributes>
    <attributes store="02">
      <allow_purchase>0</allow_purchase>
      <visibility>none</visibility>
    </attributes>
    <attributes store="66">
      <allow_purchase>0</allow_purchase>
      <visibility>none</visibility>
    </attributes>
    <links>
      <link type="relation"/>
    </links>
    <type>simple</type>
  </product>
  <product>
    <sku>VOE11035750</sku>
    <name>DRIVAXEL</name>
    <status>enabled</status>
    <attributes store="admin">
      <status>1</status>
      <c4_status>8</c4_status>
      <m3_status>20</m3_status>
      <is_returnable>0</is_returnable>
      <allow_purchase>1</allow_purchase>
      <allow_guest_purchase>1</allow_guest_purchase>
      <allow_backorders>1</allow_backorders>
      <manufacturer></manufacturer>
      <c4_sysid>697207</c4_sysid>
      <updated_at>2021-01-18T09:21:32.584000</updated_at>
      <dangerous_goods>0</dangerous_goods>
      <competitor_references>&quot;&quot;</competitor_references>
      <supplier>001</supplier>
      <visibility>both</visibility>
    </attributes>
    <attributes store="01">
      <allow_purchase>0</allow_purchase>
      <allow_guest_purchase>0</allow_guest_purchase>
      <price>24801.000000</price>
      <visibility>none</visibility>
    </attributes>
    <attributes store="02">
      <allow_purchase>0</allow_purchase>
      <visibility>none</visibility>
    </attributes>
    <attributes store="66">
      <allow_purchase>0</allow_purchase>
      <visibility>none</visibility>
    </attributes>
    <links>
      <link type="relation"/>
    </links>
    <type>simple</type>
  </product>
</integrationbase>